{
  "meta": {
    "source": "한국전력공사_한전ON 사업소정보_20240913",
    "generatedAt": "2026-06-23",
    "rawRowCount": 6978,
    "officeCount": 259,
    "officesWithPhone": 256
  },
  "aliases": {
    "전주지사": "남전주지사"
  },
  "offices": {
    "강릉전력지사": {
      "officeName": "강릉전력지사",
      "officePhone": "033-640-8326",
      "officeAddress": "강원특별자치도 강릉시 회산로 408번길 17",
      "departmentName": "변전팀",
      "taskName": "변전설비 고장복구",
      "fallbackPhone": "123",
      "phoneStatus": "official_page",
      "source": "한국전력공사_한전ON 사업소정보_20240913",
      "lastCheckedAt": "2026-06-23"
    },
    "강릉지사": {
      "officeName": "강릉지사",
      "officePhone": "033-650-1273",
      "officeAddress": "강원특별자치도 강릉시 강릉대로 563",
      "departmentName": "전력공급부",
      "taskName": "안전관리 업무",
      "fallbackPhone": "123",
      "phoneStatus": "official_page",
      "source": "한국전력공사_한전ON 사업소정보_20240913",
      "lastCheckedAt": "2026-06-23"
    },
    "강원본부": {
      "officeName": "강원본부",
      "officePhone": "033-259-2425",
      "officeAddress": "강원특별자치도 춘천시 수풍골길 7",
      "departmentName": "영업총괄팀",
      "taskName": "전기사용신청 업무",
      "fallbackPhone": "123",
      "phoneStatus": "official_page",
      "source": "한국전력공사_한전ON 사업소정보_20240913",
      "lastCheckedAt": "2026-06-23"
    },
    "강원본부직할(춘천)": {
      "officeName": "강원본부직할(춘천)",
      "officePhone": "033-259-2375",
      "officeAddress": "강원특별자치도 춘천시 수풍골길 7",
      "departmentName": "전력공급부",
      "taskName": "분산형전원 연계용량관리(춘천) 및 기술검토",
      "fallbackPhone": "123",
      "phoneStatus": "official_page",
      "source": "한국전력공사_한전ON 사업소정보_20240913",
      "lastCheckedAt": "2026-06-23"
    },
    "동해전력지사": {
      "officeName": "동해전력지사",
      "officePhone": "033-530-5353",
      "officeAddress": "강원특별자치도 동해시 동해대로 5223",
      "departmentName": "송전팀",
      "taskName": "송전설비 보수계획 및 시공",
      "fallbackPhone": "123",
      "phoneStatus": "official_page",
      "source": "한국전력공사_한전ON 사업소정보_20240913",
      "lastCheckedAt": "2026-06-23"
    },
    "동해지사": {
      "officeName": "동해지사",
      "officePhone": "033-530-6274",
      "officeAddress": "강원특별자치도 동해시 천곡로 23",
      "departmentName": "전력공급팀",
      "taskName": "신증설 설계 시공",
      "fallbackPhone": "123",
      "phoneStatus": "official_page",
      "source": "한국전력공사_한전ON 사업소정보_20240913",
      "lastCheckedAt": "2026-06-23"
    },
    "삼척지사": {
      "officeName": "삼척지사",
      "officePhone": "033-570-2272",
      "officeAddress": "강원특별자치도 삼척시 오십천로 559",
      "departmentName": "전력공급팀",
      "taskName": "신증설 설계 시공",
      "fallbackPhone": "123",
      "phoneStatus": "official_page",
      "source": "한국전력공사_한전ON 사업소정보_20240913",
      "lastCheckedAt": "2026-06-23"
    },
    "속초고성지사": {
      "officeName": "속초고성지사",
      "officePhone": "033-639-4278",
      "officeAddress": "강원특별자치도 속초시 장안로 11",
      "departmentName": "전력공급팀",
      "taskName": "신증설 설계 시공",
      "fallbackPhone": "123",
      "phoneStatus": "official_page",
      "source": "한국전력공사_한전ON 사업소정보_20240913",
      "lastCheckedAt": "2026-06-23"
    },
    "양구지사": {
      "officeName": "양구지사",
      "officePhone": "033-480-1273",
      "officeAddress": "강원특별자치도 양구군 양구읍 비봉로 73번길 15",
      "departmentName": "전력공급팀",
      "taskName": "신증설 설계 시공",
      "fallbackPhone": "123",
      "phoneStatus": "official_page",
      "source": "한국전력공사_한전ON 사업소정보_20240913",
      "lastCheckedAt": "2026-06-23"
    },
    "양양지사": {
      "officeName": "양양지사",
      "officePhone": "033-670-1273",
      "officeAddress": "강원특별자치도 양양군 양양읍 복개길 23-9",
      "departmentName": "전력공급팀",
      "taskName": "신증설 설계 시공",
      "fallbackPhone": "123",
      "phoneStatus": "official_page",
      "source": "한국전력공사_한전ON 사업소정보_20240913",
      "lastCheckedAt": "2026-06-23"
    },
    "영월지사": {
      "officeName": "영월지사",
      "officePhone": "033-370-4272",
      "officeAddress": "강원특별자치도 영월군 영월읍 중앙로 239",
      "departmentName": "전력공급팀",
      "taskName": "신증설 설계 시공",
      "fallbackPhone": "123",
      "phoneStatus": "official_page",
      "source": "한국전력공사_한전ON 사업소정보_20240913",
      "lastCheckedAt": "2026-06-23"
    },
    "원주전력지사": {
      "officeName": "원주전력지사",
      "officePhone": "033-741-5353",
      "officeAddress": "강원특별자치도 원주시 호저면 감박산길 11",
      "departmentName": "송전팀",
      "taskName": "품질 및 안전관리",
      "fallbackPhone": "123",
      "phoneStatus": "official_page",
      "source": "한국전력공사_한전ON 사업소정보_20240913",
      "lastCheckedAt": "2026-06-23"
    },
    "원주지사": {
      "officeName": "원주지사",
      "officePhone": "033-741-4291",
      "officeAddress": "강원특별자치도 원주시 우산로 122",
      "departmentName": "전력공급부",
      "taskName": "분산전원(태양광 포함) 관련 업무",
      "fallbackPhone": "123",
      "phoneStatus": "official_page",
      "source": "한국전력공사_한전ON 사업소정보_20240913",
      "lastCheckedAt": "2026-06-23"
    },
    "인제지사": {
      "officeName": "인제지사",
      "officePhone": "033-460-1272",
      "officeAddress": "강원특별자치도 인제군 인제읍 인제로 135",
      "departmentName": "전력공급팀",
      "taskName": "신증설 설계 시공",
      "fallbackPhone": "123",
      "phoneStatus": "official_page",
      "source": "한국전력공사_한전ON 사업소정보_20240913",
      "lastCheckedAt": "2026-06-23"
    },
    "정선지사": {
      "officeName": "정선지사",
      "officePhone": "033-560-3272",
      "officeAddress": "강원특별자치도 정선군 정선읍 정선로 1219",
      "departmentName": "전력공급팀",
      "taskName": "신증설 설계 시공",
      "fallbackPhone": "123",
      "phoneStatus": "official_page",
      "source": "한국전력공사_한전ON 사업소정보_20240913",
      "lastCheckedAt": "2026-06-23"
    },
    "철원지사": {
      "officeName": "철원지사",
      "officePhone": "033-450-1276",
      "officeAddress": "강원특별자치도 철원군 명성로 179번길 43",
      "departmentName": "전력공급팀",
      "taskName": "전기사용신청 신/증설 설계 시공",
      "fallbackPhone": "123",
      "phoneStatus": "official_page",
      "source": "한국전력공사_한전ON 사업소정보_20240913",
      "lastCheckedAt": "2026-06-23"
    },
    "태백전력지사": {
      "officeName": "태백전력지사",
      "officePhone": "033-550-3338",
      "officeAddress": "강원특별자치도 태백시 반딧불길 44",
      "departmentName": "변전정비팀",
      "taskName": "송변전분야 전력통신설비 업무",
      "fallbackPhone": "123",
      "phoneStatus": "official_page",
      "source": "한국전력공사_한전ON 사업소정보_20240913",
      "lastCheckedAt": "2026-06-23"
    },
    "태백지사": {
      "officeName": "태백지사",
      "officePhone": "033-550-4273",
      "officeAddress": "강원특별자치도 태백시 반딧불길 7",
      "departmentName": "전력공급팀",
      "taskName": "신증설 설계 시공",
      "fallbackPhone": "123",
      "phoneStatus": "official_page",
      "source": "한국전력공사_한전ON 사업소정보_20240913",
      "lastCheckedAt": "2026-06-23"
    },
    "평창지사": {
      "officeName": "평창지사",
      "officePhone": "033-330-4272",
      "officeAddress": "강원특별자치도 평창군 평창읍 노람들1길 2",
      "departmentName": "전력공급팀",
      "taskName": "신증설 설계 시공(대화면 방림면)",
      "fallbackPhone": "123",
      "phoneStatus": "official_page",
      "source": "한국전력공사_한전ON 사업소정보_20240913",
      "lastCheckedAt": "2026-06-23"
    },
    "홍천지사": {
      "officeName": "홍천지사",
      "officePhone": "033-430-3274",
      "officeAddress": "강원특별자치도 홍천군 홍천읍 무궁화로 81",
      "departmentName": "전력공급부",
      "taskName": "사용전 점검",
      "fallbackPhone": "123",
      "phoneStatus": "official_page",
      "source": "한국전력공사_한전ON 사업소정보_20240913",
      "lastCheckedAt": "2026-06-23"
    },
    "화천지사": {
      "officeName": "화천지사",
      "officePhone": "033-440-1272",
      "officeAddress": "강원특별자치도 화천군 화천읍 산수화로 53",
      "departmentName": "전력공급팀",
      "taskName": "신증설 설계 시공",
      "fallbackPhone": "123",
      "phoneStatus": "official_page",
      "source": "한국전력공사_한전ON 사업소정보_20240913",
      "lastCheckedAt": "2026-06-23"
    },
    "횡성지사": {
      "officeName": "횡성지사",
      "officePhone": "033-340-4272",
      "officeAddress": "강원특별자치도 횡성읍 앞들서로 30",
      "departmentName": "전력공급팀",
      "taskName": "전력공급방안 검토 신증설 설계 사용전점검(갑천 공근 청일)",
      "fallbackPhone": "123",
      "phoneStatus": "official_page",
      "source": "한국전력공사_한전ON 사업소정보_20240913",
      "lastCheckedAt": "2026-06-23"
    },
    "경기본부": {
      "officeName": "경기본부",
      "officePhone": "031-230-8221",
      "officeAddress": "경기도 수원시 팔달구 중부대로 120",
      "departmentName": "영업총괄팀",
      "taskName": "소용량고객 계약변경",
      "fallbackPhone": "123",
      "phoneStatus": "official_page",
      "source": "한국전력공사_한전ON 사업소정보_20240913",
      "lastCheckedAt": "2026-06-23"
    },
    "경기본부직할": {
      "officeName": "경기본부직할",
      "officePhone": "031-230-8425",
      "officeAddress": "경기도 수원시 팔달구 중부대로 120",
      "departmentName": "전력공급부",
      "taskName": "분산형전원 연계용량 및 기술검토",
      "fallbackPhone": "123",
      "phoneStatus": "official_page",
      "source": "한국전력공사_한전ON 사업소정보_20240913",
      "lastCheckedAt": "2026-06-23"
    },
    "광명지사": {
      "officeName": "광명지사",
      "officePhone": "02-2680-3234",
      "officeAddress": "경기도 광명시 철산로 3-13",
      "departmentName": "전력공급팀",
      "taskName": "신증설 설계 시공",
      "fallbackPhone": "123",
      "phoneStatus": "official_page",
      "source": "한국전력공사_한전ON 사업소정보_20240913",
      "lastCheckedAt": "2026-06-23"
    },
    "광주지사": {
      "officeName": "광주지사",
      "officePhone": "031-760-5236",
      "officeAddress": "경기도 광주시 역동로 13(역동 27-32)",
      "departmentName": "전력공급부",
      "taskName": "저 고압 영업일반(계기이상/계약변경 등) 관련 계기 업무",
      "fallbackPhone": "123",
      "phoneStatus": "official_page",
      "source": "한국전력공사_한전ON 사업소정보_20240913",
      "lastCheckedAt": "2026-06-23"
    },
    "군포전력지사": {
      "officeName": "군포전력지사",
      "officePhone": "031-400-2351",
      "officeAddress": "경기도 군포시 송부로 12-73",
      "departmentName": "송전부",
      "taskName": "송전설비 순시점검",
      "fallbackPhone": "123",
      "phoneStatus": "official_page",
      "source": "한국전력공사_한전ON 사업소정보_20240913",
      "lastCheckedAt": "2026-06-23"
    },
    "동부전력지사": {
      "officeName": "동부전력지사",
      "officePhone": null,
      "officeAddress": "경기도 광주시 중대동 2-31",
      "departmentName": null,
      "taskName": null,
      "fallbackPhone": "123",
      "phoneStatus": "unknown",
      "source": "한국전력공사_한전ON 사업소정보_20240913",
      "lastCheckedAt": "2026-06-23"
    },
    "동용인지사": {
      "officeName": "동용인지사",
      "officePhone": "031-330-2234",
      "officeAddress": "경기도 용인시 처인구 금령로 78번길 5",
      "departmentName": "전력공급부",
      "taskName": "전력공급방안 검토- 시내",
      "fallbackPhone": "123",
      "phoneStatus": "official_page",
      "source": "한국전력공사_한전ON 사업소정보_20240913",
      "lastCheckedAt": "2026-06-23"
    },
    "서수원지사": {
      "officeName": "서수원지사",
      "officePhone": "031-228-9231",
      "officeAddress": "경기도 수원시 권선구 호매실로 46-82",
      "departmentName": "전력공급부",
      "taskName": "안전관리",
      "fallbackPhone": "123",
      "phoneStatus": "official_page",
      "source": "한국전력공사_한전ON 사업소정보_20240913",
      "lastCheckedAt": "2026-06-23"
    },
    "서용인지사": {
      "officeName": "서용인지사",
      "officePhone": "031-230-8154",
      "officeAddress": "경기도 용인시 기흥구 민속촌로 6 2층",
      "departmentName": "고객지원부",
      "taskName": "신재생에너지(PPA 상계거래 제외) 접수 및 계약 / ※ 경기본부 에너지효율부 담당",
      "fallbackPhone": "123",
      "phoneStatus": "official_page",
      "source": "한국전력공사_한전ON 사업소정보_20240913",
      "lastCheckedAt": "2026-06-23"
    },
    "서평택지사": {
      "officeName": "서평택지사",
      "officePhone": "031-230-8155",
      "officeAddress": "경기도 평택시 청북읍 청북남로 253",
      "departmentName": "고객지원부",
      "taskName": "신재생에너지(상계거래 제외) 접수 및 계약",
      "fallbackPhone": "123",
      "phoneStatus": "official_page",
      "source": "한국전력공사_한전ON 사업소정보_20240913",
      "lastCheckedAt": "2026-06-23"
    },
    "성남전력지사": {
      "officeName": "성남전력지사",
      "officePhone": "031-780-0341",
      "officeAddress": "경기도 성남시 분당구 석운로 300",
      "departmentName": "송전부",
      "taskName": "지중설비 순시점검 및 고장복구",
      "fallbackPhone": "123",
      "phoneStatus": "official_page",
      "source": "한국전력공사_한전ON 사업소정보_20240913",
      "lastCheckedAt": "2026-06-23"
    },
    "성남지사": {
      "officeName": "성남지사",
      "officePhone": "031-750-3232",
      "officeAddress": "경기도 성남시 수정구 제일로 202",
      "departmentName": "전력공급부",
      "taskName": "신증설 설계 및 시공 전력공급방안 검토 (수정구 일대 중원구)",
      "fallbackPhone": "123",
      "phoneStatus": "official_page",
      "source": "한국전력공사_한전ON 사업소정보_20240913",
      "lastCheckedAt": "2026-06-23"
    },
    "안산지사": {
      "officeName": "안산지사",
      "officePhone": "031-412-6232",
      "officeAddress": "경기도 안산시 원고잔로 25",
      "departmentName": "전력공급부",
      "taskName": "전력공급방안 검토",
      "fallbackPhone": "123",
      "phoneStatus": "official_page",
      "source": "한국전력공사_한전ON 사업소정보_20240913",
      "lastCheckedAt": "2026-06-23"
    },
    "안성지사": {
      "officeName": "안성지사",
      "officePhone": "031-670-2232",
      "officeAddress": "경기도 안성시 내혜홀1길 14",
      "departmentName": "전력공급부",
      "taskName": "전력공급방안 검토",
      "fallbackPhone": "123",
      "phoneStatus": "official_page",
      "source": "한국전력공사_한전ON 사업소정보_20240913",
      "lastCheckedAt": "2026-06-23"
    },
    "안양군포의왕지사": {
      "officeName": "안양군포의왕지사",
      "officePhone": "031-450-2234",
      "officeAddress": "경기도 안양시 동안구 귀인로 59",
      "departmentName": "전력공급부",
      "taskName": "신증설/전력공급방안/분산형전원 검토(의왕시)",
      "fallbackPhone": "123",
      "phoneStatus": "official_page",
      "source": "한국전력공사_한전ON 사업소정보_20240913",
      "lastCheckedAt": "2026-06-23"
    },
    "여주지사": {
      "officeName": "여주지사",
      "officePhone": "031-880-2233",
      "officeAddress": "경기도 여주시 세종로 93",
      "departmentName": "전력공급부",
      "taskName": "분산형 전원(태양광 등) 설계 시공",
      "fallbackPhone": "123",
      "phoneStatus": "official_page",
      "source": "한국전력공사_한전ON 사업소정보_20240913",
      "lastCheckedAt": "2026-06-23"
    },
    "오산지사": {
      "officeName": "오산지사",
      "officePhone": "031-370-2232",
      "officeAddress": "경기도 오산시 남부대로 334",
      "departmentName": "전력공급부",
      "taskName": "안전관리 품질 환경 업무",
      "fallbackPhone": "123",
      "phoneStatus": "official_page",
      "source": "한국전력공사_한전ON 사업소정보_20240913",
      "lastCheckedAt": "2026-06-23"
    },
    "이천지사": {
      "officeName": "이천지사",
      "officePhone": "031-630-7234",
      "officeAddress": "경기도 이천시 이섭대천로 1264",
      "departmentName": "전력공급부",
      "taskName": "신재생(태양광) 연계",
      "fallbackPhone": "123",
      "phoneStatus": "official_page",
      "source": "한국전력공사_한전ON 사업소정보_20240913",
      "lastCheckedAt": "2026-06-23"
    },
    "평택전력지사": {
      "officeName": "평택전력지사",
      "officePhone": "031-646-0341",
      "officeAddress": "경기도 평택시 탄현로251-8",
      "departmentName": "송전부",
      "taskName": "지중선로 순시점검 및 고장복구",
      "fallbackPhone": "123",
      "phoneStatus": "official_page",
      "source": "한국전력공사_한전ON 사업소정보_20240913",
      "lastCheckedAt": "2026-06-23"
    },
    "평택지사": {
      "officeName": "평택지사",
      "officePhone": "031-650-4232",
      "officeAddress": "경기도 평택시 중앙로 219",
      "departmentName": "전력공급부",
      "taskName": "신증설 설계 및 시공 선로 용량 확인 등",
      "fallbackPhone": "123",
      "phoneStatus": "official_page",
      "source": "한국전력공사_한전ON 사업소정보_20240913",
      "lastCheckedAt": "2026-06-23"
    },
    "하남지사": {
      "officeName": "하남지사",
      "officePhone": "031-790-2233",
      "officeAddress": "경기도 하남시 검단산로 233",
      "departmentName": "전력공급부",
      "taskName": "신증설 설계 및 공사(미사 선 신장 창우 천현 하사창 상사창 상산곡 하산곡) / 분산형전원총괄",
      "fallbackPhone": "123",
      "phoneStatus": "official_page",
      "source": "한국전력공사_한전ON 사업소정보_20240913",
      "lastCheckedAt": "2026-06-23"
    },
    "화성지사": {
      "officeName": "화성지사",
      "officePhone": "031-369-1232",
      "officeAddress": "경기도 화성시 마도면 마도북로 403",
      "departmentName": "전력공급부",
      "taskName": "전력공급방안 검토",
      "fallbackPhone": "123",
      "phoneStatus": "official_page",
      "source": "한국전력공사_한전ON 사업소정보_20240913",
      "lastCheckedAt": "2026-06-23"
    },
    "가평지사": {
      "officeName": "가평지사",
      "officePhone": "031-580-9235",
      "officeAddress": "경기도 가평군 가평읍 가화로 169-11",
      "departmentName": "고객지원팀",
      "taskName": "전기사용신청 지장전주이설 접수 고압고객관리(설악면/상면/조종면)",
      "fallbackPhone": "123",
      "phoneStatus": "official_page",
      "source": "한국전력공사_한전ON 사업소정보_20240913",
      "lastCheckedAt": "2026-06-23"
    },
    "경기북부본부": {
      "officeName": "경기북부본부",
      "officePhone": "031-849-1424",
      "officeAddress": "경기도 의정부시 용민로19번길 80",
      "departmentName": "전력공급팀",
      "taskName": "신증설 설계 시공",
      "fallbackPhone": "123",
      "phoneStatus": "official_page",
      "source": "한국전력공사_한전ON 사업소정보_20240913",
      "lastCheckedAt": "2026-06-23"
    },
    "경기북부본부직할": {
      "officeName": "경기북부본부직할",
      "officePhone": "031-849-1243",
      "officeAddress": "경기도 의정부시 용민로19번길 80",
      "departmentName": "전력공급부",
      "taskName": "태양광 EV",
      "fallbackPhone": "123",
      "phoneStatus": "official_page",
      "source": "한국전력공사_한전ON 사업소정보_20240913",
      "lastCheckedAt": "2026-06-23"
    },
    "고양전력지사": {
      "officeName": "고양전력지사",
      "officePhone": "031-934-2352",
      "officeAddress": "경기도 고양시 덕양구 호국로 803",
      "departmentName": "송전부",
      "taskName": "송전설비 순시점검",
      "fallbackPhone": "123",
      "phoneStatus": "official_page",
      "source": "한국전력공사_한전ON 사업소정보_20240913",
      "lastCheckedAt": "2026-06-23"
    },
    "고양지사": {
      "officeName": "고양지사",
      "officePhone": "031-920-4222",
      "officeAddress": "경기도 고양시 일산동구 장백로 39",
      "departmentName": "전력공급부",
      "taskName": "신증설 계기 업무 사용전 점검",
      "fallbackPhone": "123",
      "phoneStatus": "official_page",
      "source": "한국전력공사_한전ON 사업소정보_20240913",
      "lastCheckedAt": "2026-06-23"
    },
    "구리전력지사": {
      "officeName": "구리전력지사",
      "officePhone": "031-579-7332",
      "officeAddress": "경기도 구리시 안골로 31",
      "departmentName": "변전팀",
      "taskName": "변전설비 유지보수",
      "fallbackPhone": "123",
      "phoneStatus": "official_page",
      "source": "한국전력공사_한전ON 사업소정보_20240913",
      "lastCheckedAt": "2026-06-23"
    },
    "구리지사": {
      "officeName": "구리지사",
      "officePhone": "031-560-3268",
      "officeAddress": "경기도 구리시 안골로 31",
      "departmentName": "전력공급부",
      "taskName": "운영실(고장접수/복구 및 선로순시)",
      "fallbackPhone": "123",
      "phoneStatus": "official_page",
      "source": "한국전력공사_한전ON 사업소정보_20240913",
      "lastCheckedAt": "2026-06-23"
    },
    "남양주지사": {
      "officeName": "남양주지사",
      "officePhone": "031-570-9227",
      "officeAddress": "경기도 남양주시 다산지금로 163번길 89",
      "departmentName": "전력공급부",
      "taskName": "신증설 신축 지장전주 설계 및 시공(수동 와부 수석) 협력회사/기능인력/감리용역 관리",
      "fallbackPhone": "123",
      "phoneStatus": "official_page",
      "source": "한국전력공사_한전ON 사업소정보_20240913",
      "lastCheckedAt": "2026-06-23"
    },
    "동두천지사": {
      "officeName": "동두천지사",
      "officePhone": "031-860-8268",
      "officeAddress": "경기도 동두천시 평화로 2262",
      "departmentName": "전력공급부",
      "taskName": "운영실(고장접수/복구 및 선로순시)",
      "fallbackPhone": "123",
      "phoneStatus": "official_page",
      "source": "한국전력공사_한전ON 사업소정보_20240913",
      "lastCheckedAt": "2026-06-23"
    },
    "양평지사": {
      "officeName": "양평지사",
      "officePhone": "031-770-1225",
      "officeAddress": "경기도 양평군 강상면 강남로 933",
      "departmentName": "전력공급부",
      "taskName": "신규 영업일반(고압)(서종 양서 개군 지평)분산형전원공사 총괄 AMI 총괄",
      "fallbackPhone": "123",
      "phoneStatus": "official_page",
      "source": "한국전력공사_한전ON 사업소정보_20240913",
      "lastCheckedAt": "2026-06-23"
    },
    "연천지사": {
      "officeName": "연천지사",
      "officePhone": "031-839-3278",
      "officeAddress": "경기도 연천군 전곡읍 전곡로 15",
      "departmentName": "전력공급팀",
      "taskName": "신증설 설계 시공",
      "fallbackPhone": "123",
      "phoneStatus": "official_page",
      "source": "한국전력공사_한전ON 사업소정보_20240913",
      "lastCheckedAt": "2026-06-23"
    },
    "파주지사": {
      "officeName": "파주지사",
      "officePhone": "031-940-2236",
      "officeAddress": "경기도 파주시 금바위로 60",
      "departmentName": "전력공급부",
      "taskName": "고압 계기신증설(운정교하[와동문발송촌산남 제외])조리읍",
      "fallbackPhone": "123",
      "phoneStatus": "official_page",
      "source": "한국전력공사_한전ON 사업소정보_20240913",
      "lastCheckedAt": "2026-06-23"
    },
    "포천지사": {
      "officeName": "포천지사",
      "officePhone": "031-539-0217",
      "officeAddress": "경기도 포천시 원모루로 12",
      "departmentName": "전력공급부",
      "taskName": "분산형전원",
      "fallbackPhone": "123",
      "phoneStatus": "official_page",
      "source": "한국전력공사_한전ON 사업소정보_20240913",
      "lastCheckedAt": "2026-06-23"
    },
    "거제지사": {
      "officeName": "거제지사",
      "officePhone": "055-630-2242",
      "officeAddress": "경남 거제시 서문로3길 21",
      "departmentName": "전력공급부",
      "taskName": "(전력공급팀) 신증설 점검 고압송전 계기이상(시험 교환)",
      "fallbackPhone": "123",
      "phoneStatus": "official_page",
      "source": "한국전력공사_한전ON 사업소정보_20240913",
      "lastCheckedAt": "2026-06-23"
    },
    "거창지사": {
      "officeName": "거창지사",
      "officePhone": "055-940-2232",
      "officeAddress": "경남 거창군 거창읍 강남로 246",
      "departmentName": "전력공급팀",
      "taskName": "신증설 설계 시공",
      "fallbackPhone": "123",
      "phoneStatus": "official_page",
      "source": "한국전력공사_한전ON 사업소정보_20240913",
      "lastCheckedAt": "2026-06-23"
    },
    "경남본부": {
      "officeName": "경남본부",
      "officePhone": "055-717-2248",
      "officeAddress": "경남 창원시 성산구 중앙대로210번길 13",
      "departmentName": "전력공급부",
      "taskName": "분산형전원 연계정보",
      "fallbackPhone": "123",
      "phoneStatus": "official_page",
      "source": "한국전력공사_한전ON 사업소정보_20240913",
      "lastCheckedAt": "2026-06-23"
    },
    "경남본부직할": {
      "officeName": "경남본부직할",
      "officePhone": "055-717-2244",
      "officeAddress": "경남 창원시 성산구 중앙대로210번길 13",
      "departmentName": "전력공급부",
      "taskName": "분산형전원 공급방안검토 및 연계용량 조회",
      "fallbackPhone": "123",
      "phoneStatus": "official_page",
      "source": "한국전력공사_한전ON 사업소정보_20240913",
      "lastCheckedAt": "2026-06-23"
    },
    "고성지사": {
      "officeName": "고성지사",
      "officePhone": "055-670-3233",
      "officeAddress": "경남 고성군 고성읍 성내로 162",
      "departmentName": "전력공급팀",
      "taskName": "신증설 설계 시공",
      "fallbackPhone": "123",
      "phoneStatus": "official_page",
      "source": "한국전력공사_한전ON 사업소정보_20240913",
      "lastCheckedAt": "2026-06-23"
    },
    "남해지사": {
      "officeName": "남해지사",
      "officePhone": "055-860-2232",
      "officeAddress": "경남 남해군 남해읍 남해대로 2962",
      "departmentName": "전력공급팀",
      "taskName": "신증설 설계 시공(설천고현서면)",
      "fallbackPhone": "123",
      "phoneStatus": "official_page",
      "source": "한국전력공사_한전ON 사업소정보_20240913",
      "lastCheckedAt": "2026-06-23"
    },
    "마산지사": {
      "officeName": "마산지사",
      "officePhone": "055-290-2232",
      "officeAddress": "경남 창원시 마산회원구3.15대로 966",
      "departmentName": "전력공급부",
      "taskName": "(배전파트)신증설 설계 시공",
      "fallbackPhone": "123",
      "phoneStatus": "official_page",
      "source": "한국전력공사_한전ON 사업소정보_20240913",
      "lastCheckedAt": "2026-06-23"
    },
    "밀양지사": {
      "officeName": "밀양지사",
      "officePhone": "055-350-2233",
      "officeAddress": "경남 밀양시 가곡7길 30",
      "departmentName": "전력공급부",
      "taskName": "안전관리",
      "fallbackPhone": "123",
      "phoneStatus": "official_page",
      "source": "한국전력공사_한전ON 사업소정보_20240913",
      "lastCheckedAt": "2026-06-23"
    },
    "사천지사": {
      "officeName": "사천지사",
      "officePhone": "055-830-3233",
      "officeAddress": "경남 사천시 동금6길 28",
      "departmentName": "전력공급부",
      "taskName": "(전력공급파트)전력공급방안 검토",
      "fallbackPhone": "123",
      "phoneStatus": "official_page",
      "source": "한국전력공사_한전ON 사업소정보_20240913",
      "lastCheckedAt": "2026-06-23"
    },
    "산청지사": {
      "officeName": "산청지사",
      "officePhone": "055-970-4232",
      "officeAddress": "경남 산청군 산청읍 웅석봉로 45",
      "departmentName": "전력공급팀",
      "taskName": "신증설 설계 시공",
      "fallbackPhone": "123",
      "phoneStatus": "official_page",
      "source": "한국전력공사_한전ON 사업소정보_20240913",
      "lastCheckedAt": "2026-06-23"
    },
    "의령지사": {
      "officeName": "의령지사",
      "officePhone": "055-570-3232",
      "officeAddress": "경남 의령군 의령읍 의병로 181",
      "departmentName": "전력공급팀",
      "taskName": "(전력공급팀) 신증설 설계 배전선로이설 전력공급방안검토 (의령읍 정곡면 용덕면)",
      "fallbackPhone": "123",
      "phoneStatus": "official_page",
      "source": "한국전력공사_한전ON 사업소정보_20240913",
      "lastCheckedAt": "2026-06-23"
    },
    "진주전력지사": {
      "officeName": "진주전력지사",
      "officePhone": "055-760-6334",
      "officeAddress": "경남 진주시 도동로135번길 6",
      "departmentName": "변전부",
      "taskName": "변전설비 유지보수",
      "fallbackPhone": "123",
      "phoneStatus": "official_page",
      "source": "한국전력공사_한전ON 사업소정보_20240913",
      "lastCheckedAt": "2026-06-23"
    },
    "진주지사": {
      "officeName": "진주지사",
      "officePhone": "055-750-3232",
      "officeAddress": "경남 진주시 동진로 279",
      "departmentName": "전력공급부",
      "taskName": "(배전파트)안전관리 품질 환경 업무",
      "fallbackPhone": "123",
      "phoneStatus": "official_page",
      "source": "한국전력공사_한전ON 사업소정보_20240913",
      "lastCheckedAt": "2026-06-23"
    },
    "진해지사": {
      "officeName": "진해지사",
      "officePhone": "055-540-2273",
      "officeAddress": "경남 창원시 진해구 여좌천로 122",
      "departmentName": "전력공급팀",
      "taskName": "신증설 설계 시공",
      "fallbackPhone": "123",
      "phoneStatus": "official_page",
      "source": "한국전력공사_한전ON 사업소정보_20240913",
      "lastCheckedAt": "2026-06-23"
    },
    "창녕지사": {
      "officeName": "창녕지사",
      "officePhone": "055-530-3224",
      "officeAddress": "경남 창녕군 창녕읍 남창녕로 71",
      "departmentName": "전력공급팀",
      "taskName": "신증설 설계 시공",
      "fallbackPhone": "123",
      "phoneStatus": "official_page",
      "source": "한국전력공사_한전ON 사업소정보_20240913",
      "lastCheckedAt": "2026-06-23"
    },
    "통영전력지사": {
      "officeName": "통영전력지사",
      "officePhone": "055-650-7352",
      "officeAddress": "경남 통영시 통영해안로 436(정량동)",
      "departmentName": "송전팀",
      "taskName": "품질 및 안전관리",
      "fallbackPhone": "123",
      "phoneStatus": "official_page",
      "source": "한국전력공사_한전ON 사업소정보_20240913",
      "lastCheckedAt": "2026-06-23"
    },
    "통영지사": {
      "officeName": "통영지사",
      "officePhone": "055-640-2232",
      "officeAddress": "경남 통영시 광도면 죽림2로 25-40",
      "departmentName": "전력공급부",
      "taskName": "사용전 점검",
      "fallbackPhone": "123",
      "phoneStatus": "official_page",
      "source": "한국전력공사_한전ON 사업소정보_20240913",
      "lastCheckedAt": "2026-06-23"
    },
    "하동지사": {
      "officeName": "하동지사",
      "officePhone": "055-880-5245",
      "officeAddress": "경남 하동군 하동읍 경서대로 83",
      "departmentName": "전력공급팀",
      "taskName": "저압 신증설 송전업무 PPA 상계 신증설 송전 업무 전기차충전소 K-BEMS 관련",
      "fallbackPhone": "123",
      "phoneStatus": "official_page",
      "source": "한국전력공사_한전ON 사업소정보_20240913",
      "lastCheckedAt": "2026-06-23"
    },
    "함안전력지사": {
      "officeName": "함안전력지사",
      "officePhone": "055-589-5349",
      "officeAddress": "경남 함안군 칠원면 석전5길 7-52",
      "departmentName": "송전부",
      "taskName": "송전설비 보수계획 및 시공",
      "fallbackPhone": "123",
      "phoneStatus": "official_page",
      "source": "한국전력공사_한전ON 사업소정보_20240913",
      "lastCheckedAt": "2026-06-23"
    },
    "함안지사": {
      "officeName": "함안지사",
      "officePhone": "055-580-4235",
      "officeAddress": "경남 함안군 가야읍 함마대로 1490",
      "departmentName": "전력공급팀",
      "taskName": "(전력공급팀) 신증설 설계 시공",
      "fallbackPhone": "123",
      "phoneStatus": "official_page",
      "source": "한국전력공사_한전ON 사업소정보_20240913",
      "lastCheckedAt": "2026-06-23"
    },
    "함양지사": {
      "officeName": "함양지사",
      "officePhone": "055-960-2233",
      "officeAddress": "경남 함양군 함양읍 함양로 1207",
      "departmentName": "전력공급팀",
      "taskName": "신증설 내선계기업무",
      "fallbackPhone": "123",
      "phoneStatus": "official_page",
      "source": "한국전력공사_한전ON 사업소정보_20240913",
      "lastCheckedAt": "2026-06-23"
    },
    "합천지사": {
      "officeName": "합천지사",
      "officePhone": "055-930-2232",
      "officeAddress": "경남 합천군 합천읍 대야로 921",
      "departmentName": "전력공급팀",
      "taskName": "신증설 설계 시공",
      "fallbackPhone": "123",
      "phoneStatus": "official_page",
      "source": "한국전력공사_한전ON 사업소정보_20240913",
      "lastCheckedAt": "2026-06-23"
    },
    "경북본부직할": {
      "officeName": "경북본부직할",
      "officePhone": "054-850-2239",
      "officeAddress": "경북 안동시 강남1길 9",
      "departmentName": "전력공급부",
      "taskName": "전력공급방안 검토(태양광 관련 분산형 전원 제외) ",
      "fallbackPhone": "123",
      "phoneStatus": "official_page",
      "source": "한국전력공사_한전ON 사업소정보_20240913",
      "lastCheckedAt": "2026-06-23"
    },
    "구미전력지사": {
      "officeName": "구미전력지사",
      "officePhone": "054-479-9352",
      "officeAddress": "경북 구미시 산동면 적림3길 60-5",
      "departmentName": "송전팀",
      "taskName": "품질 및 안전관리",
      "fallbackPhone": "123",
      "phoneStatus": "official_page",
      "source": "한국전력공사_한전ON 사업소정보_20240913",
      "lastCheckedAt": "2026-06-23"
    },
    "구미지사": {
      "officeName": "구미지사",
      "officePhone": "054-450-2292",
      "officeAddress": "경북 구미시 백산로 166",
      "departmentName": "전력공급부",
      "taskName": "담당지역 신규 및 신증축 지장주 설계시공(고아읍 도량동 봉곡동 부곡동 지산동 양호동 장천면 칠곡군 가산면 아포읍 대성리 석적읍 중리) 분산형전원 용량 관리 지자체요청 지중화 사업 관리",
      "fallbackPhone": "123",
      "phoneStatus": "official_page",
      "source": "한국전력공사_한전ON 사업소정보_20240913",
      "lastCheckedAt": "2026-06-23"
    },
    "군위지사": {
      "officeName": "군위지사",
      "officePhone": "054-380-2233",
      "officeAddress": "대구광역시 군위군 군위읍 중앙5길 7-14(서부리 420-5)",
      "departmentName": "고객지원팀",
      "taskName": "전기사용신청 업무",
      "fallbackPhone": "123",
      "phoneStatus": "official_page",
      "source": "한국전력공사_한전ON 사업소정보_20240913",
      "lastCheckedAt": "2026-06-23"
    },
    "문경지사": {
      "officeName": "문경지사",
      "officePhone": "054-550-2274",
      "officeAddress": "경북 문경시 모전로 75",
      "departmentName": "전력공급팀",
      "taskName": "신증설 설계 시공",
      "fallbackPhone": "123",
      "phoneStatus": "official_page",
      "source": "한국전력공사_한전ON 사업소정보_20240913",
      "lastCheckedAt": "2026-06-23"
    },
    "봉화지사": {
      "officeName": "봉화지사",
      "officePhone": "054-679-2236",
      "officeAddress": "경북 봉화군 봉화읍 내성로 42",
      "departmentName": "전력공급팀",
      "taskName": "신증설 설계 시공 지장전주 이설",
      "fallbackPhone": "123",
      "phoneStatus": "official_page",
      "source": "한국전력공사_한전ON 사업소정보_20240913",
      "lastCheckedAt": "2026-06-23"
    },
    "상주지사": {
      "officeName": "상주지사",
      "officePhone": "054-530-2158",
      "officeAddress": "경북 상주시 경상대로 3051-19",
      "departmentName": "전력공급부",
      "taskName": "분산형전원 환경",
      "fallbackPhone": "123",
      "phoneStatus": "official_page",
      "source": "한국전력공사_한전ON 사업소정보_20240913",
      "lastCheckedAt": "2026-06-23"
    },
    "영양지사": {
      "officeName": "영양지사",
      "officePhone": "054-680-4273",
      "officeAddress": "경북 영양군 영양읍 중앙로 65-5",
      "departmentName": "전력공급팀",
      "taskName": "신증설 설계 시공",
      "fallbackPhone": "123",
      "phoneStatus": "official_page",
      "source": "한국전력공사_한전ON 사업소정보_20240913",
      "lastCheckedAt": "2026-06-23"
    },
    "영주전력지사": {
      "officeName": "영주전력지사",
      "officePhone": "054-630-3352",
      "officeAddress": "경북 영주시 장수면 충효로 2119",
      "departmentName": "송전팀",
      "taskName": "송전설비 보수계획 및 시공",
      "fallbackPhone": "123",
      "phoneStatus": "official_page",
      "source": "한국전력공사_한전ON 사업소정보_20240913",
      "lastCheckedAt": "2026-06-23"
    },
    "영주지사": {
      "officeName": "영주지사",
      "officePhone": "054-630-2267",
      "officeAddress": "경북 영주시 구성로 370",
      "departmentName": "전력공급부",
      "taskName": "품질 환경 업무",
      "fallbackPhone": "123",
      "phoneStatus": "official_page",
      "source": "한국전력공사_한전ON 사업소정보_20240913",
      "lastCheckedAt": "2026-06-23"
    },
    "예천지사": {
      "officeName": "예천지사",
      "officePhone": "054-650-2277",
      "officeAddress": "경북 예천군 예천읍 효자로 170",
      "departmentName": "전력공급팀",
      "taskName": "신증설 계기 고압송전 업무",
      "fallbackPhone": "123",
      "phoneStatus": "official_page",
      "source": "한국전력공사_한전ON 사업소정보_20240913",
      "lastCheckedAt": "2026-06-23"
    },
    "울진지사": {
      "officeName": "울진지사",
      "officePhone": "054-780-3272",
      "officeAddress": "경북 울진군 울진읍 울진북로 447",
      "departmentName": "전력공급팀",
      "taskName": "신증설 설계 시공",
      "fallbackPhone": "123",
      "phoneStatus": "official_page",
      "source": "한국전력공사_한전ON 사업소정보_20240913",
      "lastCheckedAt": "2026-06-23"
    },
    "의성지사": {
      "officeName": "의성지사",
      "officePhone": "054-830-2245",
      "officeAddress": "경북 의성군 의성읍 경북대로 5644-9",
      "departmentName": "전력공급부",
      "taskName": "신증설 설계 시공 태양광(다인안사단북신평비안면)",
      "fallbackPhone": "123",
      "phoneStatus": "official_page",
      "source": "한국전력공사_한전ON 사업소정보_20240913",
      "lastCheckedAt": "2026-06-23"
    },
    "청송지사": {
      "officeName": "청송지사",
      "officePhone": "054-870-4272",
      "officeAddress": "경북 청송군 청송읍 중앙로 205",
      "departmentName": "전력공급팀",
      "taskName": "신증설 설계 시공",
      "fallbackPhone": "123",
      "phoneStatus": "official_page",
      "source": "한국전력공사_한전ON 사업소정보_20240913",
      "lastCheckedAt": "2026-06-23"
    },
    "강진전력지사": {
      "officeName": "강진전력지사",
      "officePhone": "061-430-2320",
      "officeAddress": "전남 강진군 성전면 무위사로 156-48",
      "departmentName": "송전부",
      "taskName": "품질 및 안전관리",
      "fallbackPhone": "123",
      "phoneStatus": "official_page",
      "source": "한국전력공사_한전ON 사업소정보_20240913",
      "lastCheckedAt": "2026-06-23"
    },
    "강진지사": {
      "officeName": "강진지사",
      "officePhone": "061-430-2218",
      "officeAddress": "전남 강진군 강진읍 목리길 50",
      "departmentName": "고객지원팀",
      "taskName": "신증설 배전선로이설",
      "fallbackPhone": "123",
      "phoneStatus": "official_page",
      "source": "한국전력공사_한전ON 사업소정보_20240913",
      "lastCheckedAt": "2026-06-23"
    },
    "고흥지사": {
      "officeName": "고흥지사",
      "officePhone": "061-830-1233",
      "officeAddress": "전남 고흥군 고흥읍 고흥로 1887",
      "departmentName": "전력공급부",
      "taskName": "신재생에너지(태양광)관련 업무",
      "fallbackPhone": "123",
      "phoneStatus": "official_page",
      "source": "한국전력공사_한전ON 사업소정보_20240913",
      "lastCheckedAt": "2026-06-23"
    },
    "곡성지사": {
      "officeName": "곡성지사",
      "officePhone": "061-360-1233",
      "officeAddress": "전남 곡성군 곡성읍 곡성로 795",
      "departmentName": "전력공급팀",
      "taskName": "신증설/배전선로이설 설계 및 시공 전력공급방안 검토(겸면오산면)",
      "fallbackPhone": "123",
      "phoneStatus": "official_page",
      "source": "한국전력공사_한전ON 사업소정보_20240913",
      "lastCheckedAt": "2026-06-23"
    },
    "광산지사": {
      "officeName": "광산지사",
      "officePhone": "062-940-3232",
      "officeAddress": "광주광역시 광산구 소촌로 3",
      "departmentName": "전력공급부",
      "taskName": "신증설 및 PPA상계거래 설계 시공 업무",
      "fallbackPhone": "123",
      "phoneStatus": "official_page",
      "source": "한국전력공사_한전ON 사업소정보_20240913",
      "lastCheckedAt": "2026-06-23"
    },
    "광양지사": {
      "officeName": "광양지사",
      "officePhone": "061-798-4232",
      "officeAddress": "전남 광양시 중동로 20",
      "departmentName": "전력공급부",
      "taskName": "전력공급방안 검토",
      "fallbackPhone": "123",
      "phoneStatus": "official_page",
      "source": "한국전력공사_한전ON 사업소정보_20240913",
      "lastCheckedAt": "2026-06-23"
    },
    "광주전남본부": {
      "officeName": "광주전남본부",
      "officePhone": "062-260-5215",
      "officeAddress": "광주광역시 북구 우치로 222",
      "departmentName": "고객지원부",
      "taskName": "지장전주 이설 업무",
      "fallbackPhone": "123",
      "phoneStatus": "official_page",
      "source": "한국전력공사_한전ON 사업소정보_20240913",
      "lastCheckedAt": "2026-06-23"
    },
    "광주전남본부직할": {
      "officeName": "광주전남본부직할",
      "officePhone": "062-260-5232",
      "officeAddress": "광주광역시 북구 우치로 222",
      "departmentName": "전력공급부",
      "taskName": "신증설 설계 시공",
      "fallbackPhone": "123",
      "phoneStatus": "official_page",
      "source": "한국전력공사_한전ON 사업소정보_20240913",
      "lastCheckedAt": "2026-06-23"
    },
    "광주전력지사": {
      "officeName": "광주전력지사",
      "officePhone": "062-260-4312",
      "officeAddress": "광주광역시 북구 장운길 130",
      "departmentName": "송전팀",
      "taskName": "보안 방호설비 및 총무업무",
      "fallbackPhone": "123",
      "phoneStatus": "official_page",
      "source": "한국전력공사_한전ON 사업소정보_20240913",
      "lastCheckedAt": "2026-06-23"
    },
    "구례지사": {
      "officeName": "구례지사",
      "officePhone": "061-780-1232",
      "officeAddress": "전남 구례군 구례읍 구례로 397",
      "departmentName": "전력공급팀",
      "taskName": "신증설 설계 시공",
      "fallbackPhone": "123",
      "phoneStatus": "official_page",
      "source": "한국전력공사_한전ON 사업소정보_20240913",
      "lastCheckedAt": "2026-06-23"
    },
    "기획관리실": {
      "officeName": "기획관리실",
      "officePhone": "062-260-5189",
      "officeAddress": "광주광역시 북구 우치로 222",
      "departmentName": "전략경영부",
      "taskName": "송무 및 공정거래업무",
      "fallbackPhone": "123",
      "phoneStatus": "official_page",
      "source": "한국전력공사_한전ON 사업소정보_20240913",
      "lastCheckedAt": "2026-06-23"
    },
    "나주지사": {
      "officeName": "나주지사",
      "officePhone": "061-330-2235",
      "officeAddress": "전남 나주시 왕건길 53",
      "departmentName": "전력공급부",
      "taskName": "태양광 선로관리",
      "fallbackPhone": "123",
      "phoneStatus": "official_page",
      "source": "한국전력공사_한전ON 사업소정보_20240913",
      "lastCheckedAt": "2026-06-23"
    },
    "담양지사": {
      "officeName": "담양지사",
      "officePhone": "061-380-0231",
      "officeAddress": "전남 담양군 담양읍 무정로 25",
      "departmentName": "전력공급팀",
      "taskName": "신증설 배전선로 이설 설계 및 시공(대전면봉산면)",
      "fallbackPhone": "123",
      "phoneStatus": "official_page",
      "source": "한국전력공사_한전ON 사업소정보_20240913",
      "lastCheckedAt": "2026-06-23"
    },
    "목포전력지사": {
      "officeName": "목포전력지사",
      "officePhone": "061-989-3351",
      "officeAddress": "전남 무안군 삼향읍 후광대로282",
      "departmentName": "송전팀",
      "taskName": "송전팀장",
      "fallbackPhone": "123",
      "phoneStatus": "official_page",
      "source": "한국전력공사_한전ON 사업소정보_20240913",
      "lastCheckedAt": "2026-06-23"
    },
    "목포지사": {
      "officeName": "목포지사",
      "officePhone": "061-270-2232",
      "officeAddress": "전남 목포시 삼학로 370",
      "departmentName": "전력공급부",
      "taskName": "유도장해 고조파 관련 업무",
      "fallbackPhone": "123",
      "phoneStatus": "official_page",
      "source": "한국전력공사_한전ON 사업소정보_20240913",
      "lastCheckedAt": "2026-06-23"
    },
    "무안지사": {
      "officeName": "무안지사",
      "officePhone": "061-450-0213",
      "officeAddress": "전남 무안군 무안읍 무안중앙로 76-1",
      "departmentName": "고객지원팀",
      "taskName": "전기사용신청 업무",
      "fallbackPhone": "123",
      "phoneStatus": "official_page",
      "source": "한국전력공사_한전ON 사업소정보_20240913",
      "lastCheckedAt": "2026-06-23"
    },
    "보성지사": {
      "officeName": "보성지사",
      "officePhone": "061-850-2234",
      "officeAddress": "전남 보성군 보성읍 송재로 53",
      "departmentName": "전력공급팀",
      "taskName": "신증설 설계 시공",
      "fallbackPhone": "123",
      "phoneStatus": "official_page",
      "source": "한국전력공사_한전ON 사업소정보_20240913",
      "lastCheckedAt": "2026-06-23"
    },
    "서광주지사": {
      "officeName": "서광주지사",
      "officePhone": "062-360-6232",
      "officeAddress": "광주광역시 서구 경열로 39",
      "departmentName": "전력공급부",
      "taskName": "전력공급방안 검토",
      "fallbackPhone": "123",
      "phoneStatus": "official_page",
      "source": "한국전력공사_한전ON 사업소정보_20240913",
      "lastCheckedAt": "2026-06-23"
    },
    "순천전력지사": {
      "officeName": "순천전력지사",
      "officePhone": "061-740-3345",
      "officeAddress": "전남 순천시 조례동 우명길 9",
      "departmentName": "변전부",
      "taskName": "변전설비 고장복구",
      "fallbackPhone": "123",
      "phoneStatus": "official_page",
      "source": "한국전력공사_한전ON 사업소정보_20240913",
      "lastCheckedAt": "2026-06-23"
    },
    "순천지사": {
      "officeName": "순천지사",
      "officePhone": "061-750-2232",
      "officeAddress": "전남 순천시 순천대 2길 13",
      "departmentName": "전력공급부",
      "taskName": "신증설 설계 시공",
      "fallbackPhone": "123",
      "phoneStatus": "official_page",
      "source": "한국전력공사_한전ON 사업소정보_20240913",
      "lastCheckedAt": "2026-06-23"
    },
    "신안지사": {
      "officeName": "신안지사",
      "officePhone": "061-260-6231",
      "officeAddress": "전남 신안군 안좌면 안좌동부길 836",
      "departmentName": "전력공급팀",
      "taskName": "신증설 설계 시공",
      "fallbackPhone": "123",
      "phoneStatus": "official_page",
      "source": "한국전력공사_한전ON 사업소정보_20240913",
      "lastCheckedAt": "2026-06-23"
    },
    "여수지사": {
      "officeName": "여수지사",
      "officePhone": "061-650-2266",
      "officeAddress": "전남 여수시 좌수영로 416",
      "departmentName": "배전운영부",
      "taskName": "운영실(고장접수/복구 및 선로순시)",
      "fallbackPhone": "123",
      "phoneStatus": "official_page",
      "source": "한국전력공사_한전ON 사업소정보_20240913",
      "lastCheckedAt": "2026-06-23"
    },
    "영광지사": {
      "officeName": "영광지사",
      "officePhone": "061-350-2232",
      "officeAddress": "전남 영광군 영광읍 천년로 1464",
      "departmentName": "전력공급팀",
      "taskName": "[지역별] 신증설 및 배전선로 이설공사 설계 시공 계기입력 및 출고",
      "fallbackPhone": "123",
      "phoneStatus": "official_page",
      "source": "한국전력공사_한전ON 사업소정보_20240913",
      "lastCheckedAt": "2026-06-23"
    },
    "영암지사": {
      "officeName": "영암지사",
      "officePhone": "061-470-3232",
      "officeAddress": "전남 영암군 영암읍 서남역로 31",
      "departmentName": "전력공급부",
      "taskName": "[지역별] 신증설/신재생에너지 설계 및 시공 관련 업무",
      "fallbackPhone": "123",
      "phoneStatus": "official_page",
      "source": "한국전력공사_한전ON 사업소정보_20240913",
      "lastCheckedAt": "2026-06-23"
    },
    "완도지사": {
      "officeName": "완도지사",
      "officePhone": "061-550-0213",
      "officeAddress": "전남 완도군 완도읍 개포로62번길 6",
      "departmentName": "고객지원팀",
      "taskName": "전기사용신청 업무",
      "fallbackPhone": "123",
      "phoneStatus": "official_page",
      "source": "한국전력공사_한전ON 사업소정보_20240913",
      "lastCheckedAt": "2026-06-23"
    },
    "장성지사": {
      "officeName": "장성지사",
      "officePhone": "061-390-6231",
      "officeAddress": "전남 장성군 장성읍 보해길 30",
      "departmentName": "전력공급팀",
      "taskName": "신증설 설계 시공",
      "fallbackPhone": "123",
      "phoneStatus": "official_page",
      "source": "한국전력공사_한전ON 사업소정보_20240913",
      "lastCheckedAt": "2026-06-23"
    },
    "장흥지사": {
      "officeName": "장흥지사",
      "officePhone": "061-860-2232",
      "officeAddress": "전남 장흥군 장흥읍 중앙로 24",
      "departmentName": "전력공급팀",
      "taskName": "신증설 설계 시공",
      "fallbackPhone": "123",
      "phoneStatus": "official_page",
      "source": "한국전력공사_한전ON 사업소정보_20240913",
      "lastCheckedAt": "2026-06-23"
    },
    "전력관리처": {
      "officeName": "전력관리처",
      "officePhone": "051-604-5871",
      "officeAddress": "광주광역시 북구 우치로 222",
      "departmentName": "송전운영부",
      "taskName": "송변전 주변지역 지원",
      "fallbackPhone": "123",
      "phoneStatus": "official_page",
      "source": "한국전력공사_한전ON 사업소정보_20240913",
      "lastCheckedAt": "2026-06-23"
    },
    "전력사업처": {
      "officeName": "전력사업처",
      "officePhone": "062-260-5232",
      "officeAddress": "광주광역시 북구 우치로 222",
      "departmentName": "전력공급부",
      "taskName": "신증설 설계 시공",
      "fallbackPhone": "123",
      "phoneStatus": "official_page",
      "source": "한국전력공사_한전ON 사업소정보_20240913",
      "lastCheckedAt": "2026-06-23"
    },
    "진도지사": {
      "officeName": "진도지사",
      "officePhone": "061-540-2232",
      "officeAddress": "전남 진도군 진도읍 남동1길 25-1",
      "departmentName": "전력공급팀",
      "taskName": "신증설 설계 시공",
      "fallbackPhone": "123",
      "phoneStatus": "official_page",
      "source": "한국전력공사_한전ON 사업소정보_20240913",
      "lastCheckedAt": "2026-06-23"
    },
    "함평지사": {
      "officeName": "함평지사",
      "officePhone": "061-320-0235",
      "officeAddress": "전남 함평군 함평읍 서부길 41-14",
      "departmentName": "전력공급팀",
      "taskName": "신증설 설계 시공",
      "fallbackPhone": "123",
      "phoneStatus": "official_page",
      "source": "한국전력공사_한전ON 사업소정보_20240913",
      "lastCheckedAt": "2026-06-23"
    },
    "해남지사": {
      "officeName": "해남지사",
      "officePhone": "061-530-2239",
      "officeAddress": "전남 해남군 해남읍 북부순환로 5",
      "departmentName": "전력공급부",
      "taskName": "태양광 선로용량",
      "fallbackPhone": "123",
      "phoneStatus": "official_page",
      "source": "한국전력공사_한전ON 사업소정보_20240913",
      "lastCheckedAt": "2026-06-23"
    },
    "화순지사": {
      "officeName": "화순지사",
      "officePhone": "061-370-0235",
      "officeAddress": "전남 화순군 화순읍 충의로 11",
      "departmentName": "전력공급부",
      "taskName": "신재생에너지(태양광)관련 업무",
      "fallbackPhone": "123",
      "phoneStatus": "official_page",
      "source": "한국전력공사_한전ON 사업소정보_20240913",
      "lastCheckedAt": "2026-06-23"
    },
    "강남전력지사": {
      "officeName": "강남전력지사",
      "officePhone": "02-3496-9323",
      "officeAddress": "서울특별시 서초구 효령로 72길 60",
      "departmentName": "송전팀",
      "taskName": "송전설비 고장복구",
      "fallbackPhone": "123",
      "phoneStatus": "official_page",
      "source": "한국전력공사_한전ON 사업소정보_20240913",
      "lastCheckedAt": "2026-06-23"
    },
    "강남지사": {
      "officeName": "강남지사",
      "officePhone": "02-6445-5233",
      "officeAddress": "서울특별시 강남구 강남대로 262 (도곡동 949-3 캠코양재타워)",
      "departmentName": "전력공급부",
      "taskName": "전력공급방안 검토",
      "fallbackPhone": "123",
      "phoneStatus": "official_page",
      "source": "한국전력공사_한전ON 사업소정보_20240913",
      "lastCheckedAt": "2026-06-23"
    },
    "강동송파지사": {
      "officeName": "강동송파지사",
      "officePhone": "02-480-2244",
      "officeAddress": "서울특별시 강동구 양재대로 1318",
      "departmentName": "전력공급부",
      "taskName": "품질 분산형전원",
      "fallbackPhone": "123",
      "phoneStatus": "official_page",
      "source": "한국전력공사_한전ON 사업소정보_20240913",
      "lastCheckedAt": "2026-06-23"
    },
    "강서양천지사": {
      "officeName": "강서양천지사",
      "officePhone": "02-2640-2242",
      "officeAddress": "서울특별시 양천구 목동서로 313",
      "departmentName": "전력공급부",
      "taskName": "담당구역(마곡1·3공구방화동) 신규 공사감독 분산형전원",
      "fallbackPhone": "123",
      "phoneStatus": "official_page",
      "source": "한국전력공사_한전ON 사업소정보_20240913",
      "lastCheckedAt": "2026-06-23"
    },
    "관악동작지사": {
      "officeName": "관악동작지사",
      "officePhone": "02-580-2233",
      "officeAddress": "서울특별시 동작구 동작대로 19",
      "departmentName": "전력공급부",
      "taskName": "신규 및 증설 외선공사 설계 시공 관리(신림동)",
      "fallbackPhone": "123",
      "phoneStatus": "official_page",
      "source": "한국전력공사_한전ON 사업소정보_20240913",
      "lastCheckedAt": "2026-06-23"
    },
    "구로금천지사": {
      "officeName": "구로금천지사",
      "officePhone": "02-6440-0233",
      "officeAddress": "서울특별시 금천구 시흥대로 435 (구 메이퀸웨딩홀 2~3층)",
      "departmentName": "전력공급부",
      "taskName": "배전신규",
      "fallbackPhone": "123",
      "phoneStatus": "official_page",
      "source": "한국전력공사_한전ON 사업소정보_20240913",
      "lastCheckedAt": "2026-06-23"
    },
    "남서울본부": {
      "officeName": "남서울본부",
      "officePhone": "02-2670-2242",
      "officeAddress": "서울특별시 영등포구 문래북로 66 [전력사업처]",
      "departmentName": "배전운영팀",
      "taskName": "신증설 설계 시공",
      "fallbackPhone": "123",
      "phoneStatus": "official_page",
      "source": "한국전력공사_한전ON 사업소정보_20240913",
      "lastCheckedAt": "2026-06-23"
    },
    "남서울본부 디지털영업센터(고압 통합접수)": {
      "officeName": "남서울본부 디지털영업센터(고압 통합접수)",
      "officePhone": "02-787-8202",
      "officeAddress": "서울시 영등포구 여의동로7길5 한전남서울본부 1층고객상담실",
      "departmentName": "디지털영업센터",
      "taskName": "고압 신증설 및 영업일반(영등포구)",
      "fallbackPhone": "123",
      "phoneStatus": "official_page",
      "source": "한국전력공사_한전ON 사업소정보_20240913",
      "lastCheckedAt": "2026-06-23"
    },
    "남서울본부직할": {
      "officeName": "남서울본부직할",
      "officePhone": "02-2670-2273",
      "officeAddress": "서울특별시 영등포구 문래북로 66 [전력사업처]",
      "departmentName": "전력공급부",
      "taskName": "사용전 점검",
      "fallbackPhone": "123",
      "phoneStatus": "official_page",
      "source": "한국전력공사_한전ON 사업소정보_20240913",
      "lastCheckedAt": "2026-06-23"
    },
    "동서울전력지사": {
      "officeName": "동서울전력지사",
      "officePhone": "02-480-4322",
      "officeAddress": "경기도 하남시 감북로  80",
      "departmentName": "송전부",
      "taskName": "송전설비 순시점검",
      "fallbackPhone": "123",
      "phoneStatus": "official_page",
      "source": "한국전력공사_한전ON 사업소정보_20240913",
      "lastCheckedAt": "2026-06-23"
    },
    "서초지사": {
      "officeName": "서초지사",
      "officePhone": "02-2105-8235",
      "officeAddress": "서울특별시 서초구 효령로 72길 60",
      "departmentName": "전력공급부",
      "taskName": "신증설 설계 시공",
      "fallbackPhone": "123",
      "phoneStatus": "official_page",
      "source": "한국전력공사_한전ON 사업소정보_20240913",
      "lastCheckedAt": "2026-06-23"
    },
    "영등포전력지사": {
      "officeName": "영등포전력지사",
      "officePhone": "02-2670-4315",
      "officeAddress": "서울특별시 영등포구 경인로 878",
      "departmentName": "송전부",
      "taskName": "송전설비 보수계획 및 시공",
      "fallbackPhone": "123",
      "phoneStatus": "official_page",
      "source": "한국전력공사_한전ON 사업소정보_20240913",
      "lastCheckedAt": "2026-06-23"
    },
    "경산전력지사": {
      "officeName": "경산전력지사",
      "officePhone": "053-859-8352",
      "officeAddress": "경북 경산시 진량읍 공단8로 186",
      "departmentName": "송전팀",
      "taskName": "송전설비 보수계획 및 시공",
      "fallbackPhone": "123",
      "phoneStatus": "official_page",
      "source": "한국전력공사_한전ON 사업소정보_20240913",
      "lastCheckedAt": "2026-06-23"
    },
    "경산지사": {
      "officeName": "경산지사",
      "officePhone": "053-810-4132",
      "officeAddress": "경북 경산시 원효로 8",
      "departmentName": "전력공급부",
      "taskName": "계기이상/시험/교환 업무",
      "fallbackPhone": "123",
      "phoneStatus": "official_page",
      "source": "한국전력공사_한전ON 사업소정보_20240913",
      "lastCheckedAt": "2026-06-23"
    },
    "경주지사": {
      "officeName": "경주지사",
      "officePhone": "054-740-2132",
      "officeAddress": "경북 경주시 양정로 246",
      "departmentName": "전력공급부",
      "taskName": "신재생에너지 접속가능 용량 및 분산형 전원 기술검토 업무",
      "fallbackPhone": "123",
      "phoneStatus": "official_page",
      "source": "한국전력공사_한전ON 사업소정보_20240913",
      "lastCheckedAt": "2026-06-23"
    },
    "고령지사": {
      "officeName": "고령지사",
      "officePhone": "054-950-2223",
      "officeAddress": "경북 고령군 대가야읍 월기길 14",
      "departmentName": "고객지원팀",
      "taskName": "저압신규 신재생(태양광) 태양광 상계거래",
      "fallbackPhone": "123",
      "phoneStatus": "official_page",
      "source": "한국전력공사_한전ON 사업소정보_20240913",
      "lastCheckedAt": "2026-06-23"
    },
    "김천지사": {
      "officeName": "김천지사",
      "officePhone": "054-429-5288",
      "officeAddress": "경북 김천시 모암길 210",
      "departmentName": "전력공급부",
      "taskName": "태양광 선로 용량 검토",
      "fallbackPhone": "123",
      "phoneStatus": "official_page",
      "source": "한국전력공사_한전ON 사업소정보_20240913",
      "lastCheckedAt": "2026-06-23"
    },
    "남대구지사": {
      "officeName": "남대구지사",
      "officePhone": "053-630-2232",
      "officeAddress": "대구광역시 달성군 화원읍 비슬로 509길 26",
      "departmentName": "전력공급부",
      "taskName": "유도장해 고조파 관련 업무",
      "fallbackPhone": "123",
      "phoneStatus": "official_page",
      "source": "한국전력공사_한전ON 사업소정보_20240913",
      "lastCheckedAt": "2026-06-23"
    },
    "달성전력지사": {
      "officeName": "달성전력지사",
      "officePhone": "053-630-3352",
      "officeAddress": "대구광역시 달성군 화원읍 비슬로 539길 4",
      "departmentName": "송전부",
      "taskName": "송전설비 순시점검",
      "fallbackPhone": "123",
      "phoneStatus": "official_page",
      "source": "한국전력공사_한전ON 사업소정보_20240913",
      "lastCheckedAt": "2026-06-23"
    },
    "대구본부": {
      "officeName": "대구본부",
      "officePhone": "053-350-2414",
      "officeAddress": "대구광역시 북구 원대로 110",
      "departmentName": "수요관리팀",
      "taskName": "신재생에너지(태양광)관련 업무",
      "fallbackPhone": "123",
      "phoneStatus": "official_page",
      "source": "한국전력공사_한전ON 사업소정보_20240913",
      "lastCheckedAt": "2026-06-23"
    },
    "대구본부직할": {
      "officeName": "대구본부직할",
      "officePhone": "053-350-2408",
      "officeAddress": "대구광역시 북구 원대로 110",
      "departmentName": "전력공급부",
      "taskName": "분산형전원 연계용량 관리 및 안내 협력회사 관리",
      "fallbackPhone": "123",
      "phoneStatus": "official_page",
      "source": "한국전력공사_한전ON 사업소정보_20240913",
      "lastCheckedAt": "2026-06-23"
    },
    "동대구지사": {
      "officeName": "동대구지사",
      "officePhone": "053-757-2384",
      "officeAddress": "대구광역시 동구 화랑로 135",
      "departmentName": "전력공급부",
      "taskName": "고압 계기업무",
      "fallbackPhone": "123",
      "phoneStatus": "official_page",
      "source": "한국전력공사_한전ON 사업소정보_20240913",
      "lastCheckedAt": "2026-06-23"
    },
    "북포항지사": {
      "officeName": "북포항지사",
      "officePhone": "054-260-4231",
      "officeAddress": "경북 포항시 북구 흥해읍 흥해로 100",
      "departmentName": "전력공급팀",
      "taskName": "신증설 설계 시공",
      "fallbackPhone": "123",
      "phoneStatus": "official_page",
      "source": "한국전력공사_한전ON 사업소정보_20240913",
      "lastCheckedAt": "2026-06-23"
    },
    "서대구지사": {
      "officeName": "서대구지사",
      "officePhone": "053-550-2182",
      "officeAddress": "대구광역시 서구 달서로 85",
      "departmentName": "전력공급부",
      "taskName": "신증설 송전(달서구 고압) 영업일반(달서구 고압)",
      "fallbackPhone": "123",
      "phoneStatus": "official_page",
      "source": "한국전력공사_한전ON 사업소정보_20240913",
      "lastCheckedAt": "2026-06-23"
    },
    "성주지사": {
      "officeName": "성주지사",
      "officePhone": "053-630-2232",
      "officeAddress": "경북 성주군 성주읍 주산로 113",
      "departmentName": "전력공급팀",
      "taskName": "신증설 설계·시공 전력공급방안검토 (달서구: 상인. 송현. 본동 월성 유천 진천 대곡 도원 대천 달성군 화원읍)",
      "fallbackPhone": "123",
      "phoneStatus": "official_page",
      "source": "한국전력공사_한전ON 사업소정보_20240913",
      "lastCheckedAt": "2026-06-23"
    },
    "영덕지사": {
      "officeName": "영덕지사",
      "officePhone": "054-730-3231",
      "officeAddress": "경북 영덕군 영덕읍 영덕로 184",
      "departmentName": "전력공급팀",
      "taskName": "신증설 설계 시공(영덕읍 지품 달산 강구 남정)",
      "fallbackPhone": "123",
      "phoneStatus": "official_page",
      "source": "한국전력공사_한전ON 사업소정보_20240913",
      "lastCheckedAt": "2026-06-23"
    },
    "영천지사": {
      "officeName": "영천지사",
      "officePhone": "054-330-2242",
      "officeAddress": "경북 영천시 천문로 199",
      "departmentName": "전력공급부",
      "taskName": "분산형전원 업무(선로 용량 관리 등)",
      "fallbackPhone": "123",
      "phoneStatus": "official_page",
      "source": "한국전력공사_한전ON 사업소정보_20240913",
      "lastCheckedAt": "2026-06-23"
    },
    "울릉지사": {
      "officeName": "울릉지사",
      "officePhone": "054-790-2271",
      "officeAddress": "경북 울릉군 울릉읍 도동3길 28",
      "departmentName": "고객지원팀",
      "taskName": "신증설 설계 시공",
      "fallbackPhone": "123",
      "phoneStatus": "official_page",
      "source": "한국전력공사_한전ON 사업소정보_20240913",
      "lastCheckedAt": "2026-06-23"
    },
    "청도지사": {
      "officeName": "청도지사",
      "officePhone": "054-370-4231",
      "officeAddress": "경상북도 청도읍 청화로 219-25",
      "departmentName": "전력공급팀",
      "taskName": "o신증설 설계 시공(화양읍) 054-370-4236o신증설 설계 시공(각북풍각) 054-370-4235o신증설 설계 시공(매전금천) 054-370-4233o신증설 설계 시공(운문) 054-370-4231o신증설 설계 시공(이서) 054-370-4254o신증설 설계 시공(청도읍) 054-370-4234o신증설 설계 시공(각남) 054-370-4232",
      "fallbackPhone": "123",
      "phoneStatus": "official_page",
      "source": "한국전력공사_한전ON 사업소정보_20240913",
      "lastCheckedAt": "2026-06-23"
    },
    "칠곡전력지사": {
      "officeName": "칠곡전력지사",
      "officePhone": "054-970-3352",
      "officeAddress": "경북 칠곡군 왜관읍 닥실길 54-11",
      "departmentName": "송전팀",
      "taskName": "송전설비 순시점검",
      "fallbackPhone": "123",
      "phoneStatus": "official_page",
      "source": "한국전력공사_한전ON 사업소정보_20240913",
      "lastCheckedAt": "2026-06-23"
    },
    "칠곡지사": {
      "officeName": "칠곡지사",
      "officePhone": "054-970-3232",
      "officeAddress": "경북 칠곡군 왜관읍 구상길 178",
      "departmentName": "전력공급부",
      "taskName": "신증설 전력공급방안 검토설계시공(왜관기산)",
      "fallbackPhone": "123",
      "phoneStatus": "official_page",
      "source": "한국전력공사_한전ON 사업소정보_20240913",
      "lastCheckedAt": "2026-06-23"
    },
    "포항전력지사": {
      "officeName": "포항전력지사",
      "officePhone": "054-720-3343",
      "officeAddress": "경북 포항시 남구 오천읍 정몽주로 242-12",
      "departmentName": "송전부",
      "taskName": "송전설비 보수계획 및 시공",
      "fallbackPhone": "123",
      "phoneStatus": "official_page",
      "source": "한국전력공사_한전ON 사업소정보_20240913",
      "lastCheckedAt": "2026-06-23"
    },
    "포항지사": {
      "officeName": "포항지사",
      "officePhone": "054-271-7135",
      "officeAddress": "경북 포항시 남구 희망대로 677",
      "departmentName": "전력공급부",
      "taskName": "계기이상/시험/교환 업무",
      "fallbackPhone": "123",
      "phoneStatus": "official_page",
      "source": "한국전력공사_한전ON 사업소정보_20240913",
      "lastCheckedAt": "2026-06-23"
    },
    "공주지사": {
      "officeName": "공주지사",
      "officePhone": "041-850-2232",
      "officeAddress": "충남 공주시 우금티로 772",
      "departmentName": "전력공급부",
      "taskName": "안전관리 품질 환경 업무",
      "fallbackPhone": "123",
      "phoneStatus": "official_page",
      "source": "한국전력공사_한전ON 사업소정보_20240913",
      "lastCheckedAt": "2026-06-23"
    },
    "금산지사": {
      "officeName": "금산지사",
      "officePhone": "041-750-3216",
      "officeAddress": "충남 금산군 금산읍 후곤천길 5",
      "departmentName": "고객지원팀",
      "taskName": "저·고압 신증설 및 영업일반 배전선로이설 접수 및 정산 공가요금 청구수납 고객만족도",
      "fallbackPhone": "123",
      "phoneStatus": "official_page",
      "source": "한국전력공사_한전ON 사업소정보_20240913",
      "lastCheckedAt": "2026-06-23"
    },
    "논산지사": {
      "officeName": "논산지사",
      "officePhone": "041-746-2234",
      "officeAddress": "충남 논산시 논산대로348번길 10",
      "departmentName": "전력공급부",
      "taskName": "분산형전원관리총괄 지자체요청 지중화 업무 신규지장분산형전원(부적연산은진채운취암내동덕지반월화지지산관촉)",
      "fallbackPhone": "123",
      "phoneStatus": "official_page",
      "source": "한국전력공사_한전ON 사업소정보_20240913",
      "lastCheckedAt": "2026-06-23"
    },
    "당진지사": {
      "officeName": "당진지사",
      "officePhone": "041-350-2289",
      "officeAddress": "충남 당진시 천변2길 123",
      "departmentName": "전력공급부",
      "taskName": "분산형전원 업무 총괄  신규 수용 설계 및 공사관리(당진3동 송산 송악)",
      "fallbackPhone": "123",
      "phoneStatus": "official_page",
      "source": "한국전력공사_한전ON 사업소정보_20240913",
      "lastCheckedAt": "2026-06-23"
    },
    "대덕유성지사": {
      "officeName": "대덕유성지사",
      "officePhone": "042-333-0232",
      "officeAddress": "대전광역시 유성구 계룡로 114",
      "departmentName": "전력공급부",
      "taskName": "안전관리 품질 환경 업무",
      "fallbackPhone": "123",
      "phoneStatus": "official_page",
      "source": "한국전력공사_한전ON 사업소정보_20240913",
      "lastCheckedAt": "2026-06-23"
    },
    "대전세종충남본부": {
      "officeName": "대전세종충남본부",
      "officePhone": "042-620-2234",
      "officeAddress": "대전광역시 동구 송촌남로11번길 170",
      "departmentName": "배전총괄팀",
      "taskName": "신증설 설계 시공",
      "fallbackPhone": "123",
      "phoneStatus": "official_page",
      "source": "한국전력공사_한전ON 사업소정보_20240913",
      "lastCheckedAt": "2026-06-23"
    },
    "대전세종충남본부직할": {
      "officeName": "대전세종충남본부직할",
      "officePhone": "042-620-2231",
      "officeAddress": "대전광역시 동구 송촌남로11번길 170",
      "departmentName": "전력공급부",
      "taskName": "분산형전원 기술검토 및 보호협조검토 분산형전원 투자계획 관리 (공주 홍성 예산 금산 청양)",
      "fallbackPhone": "123",
      "phoneStatus": "official_page",
      "source": "한국전력공사_한전ON 사업소정보_20240913",
      "lastCheckedAt": "2026-06-23"
    },
    "대전전력지사": {
      "officeName": "대전전력지사",
      "officePhone": "042-333-2350",
      "officeAddress": "대전광역시 동구 대전로 422-12",
      "departmentName": "송전팀",
      "taskName": "송전설비 순시점검",
      "fallbackPhone": "123",
      "phoneStatus": "official_page",
      "source": "한국전력공사_한전ON 사업소정보_20240913",
      "lastCheckedAt": "2026-06-23"
    },
    "보령지사": {
      "officeName": "보령지사",
      "officePhone": "041-930-7233",
      "officeAddress": "충남 보령시 옥마로 60",
      "departmentName": "전력공급부",
      "taskName": "유도장해 고조파 관련 업무",
      "fallbackPhone": "123",
      "phoneStatus": "official_page",
      "source": "한국전력공사_한전ON 사업소정보_20240913",
      "lastCheckedAt": "2026-06-23"
    },
    "부여지사": {
      "officeName": "부여지사",
      "officePhone": "041-830-1233",
      "officeAddress": "충남 부여군 부여읍 성왕로396",
      "departmentName": "전력공급부",
      "taskName": "분산형전원 사전 용량검토",
      "fallbackPhone": "123",
      "phoneStatus": "official_page",
      "source": "한국전력공사_한전ON 사업소정보_20240913",
      "lastCheckedAt": "2026-06-23"
    },
    "서대전지사": {
      "officeName": "서대전지사",
      "officePhone": "042-608-2242",
      "officeAddress": "대전광역시 서구 변동중로 39",
      "departmentName": "전력공급부",
      "taskName": "계룡 : 신증설 설계 및 시공 신축 지장전주 / 분산형전원 기술검토",
      "fallbackPhone": "123",
      "phoneStatus": "official_page",
      "source": "한국전력공사_한전ON 사업소정보_20240913",
      "lastCheckedAt": "2026-06-23"
    },
    "서산전력지사": {
      "officeName": "서산전력지사",
      "officePhone": "041-661-6319",
      "officeAddress": "충남 서산시 성연면 성연2로 49",
      "departmentName": "송전부",
      "taskName": "품질 및 안전관리",
      "fallbackPhone": "123",
      "phoneStatus": "official_page",
      "source": "한국전력공사_한전ON 사업소정보_20240913",
      "lastCheckedAt": "2026-06-23"
    },
    "서산지사": {
      "officeName": "서산지사",
      "officePhone": "041-660-8232",
      "officeAddress": "충남 서산시 한마음16로 63",
      "departmentName": "전력공급부",
      "taskName": "신증설 설계 시공",
      "fallbackPhone": "123",
      "phoneStatus": "official_page",
      "source": "한국전력공사_한전ON 사업소정보_20240913",
      "lastCheckedAt": "2026-06-23"
    },
    "서천지사": {
      "officeName": "서천지사",
      "officePhone": "041-955-2233",
      "officeAddress": "충남 서천군 장항읍 장항로171번길 58",
      "departmentName": "전력공급팀",
      "taskName": "신증설 설계 시공",
      "fallbackPhone": "123",
      "phoneStatus": "official_page",
      "source": "한국전력공사_한전ON 사업소정보_20240913",
      "lastCheckedAt": "2026-06-23"
    },
    "세종전력지사": {
      "officeName": "세종전력지사",
      "officePhone": "042-388-1392",
      "officeAddress": "대전광역시 유성구 지족동로 142번길 45 스카이타워 3층",
      "departmentName": "전자제어팀",
      "taskName": "SCADA 설비 교체 및 증설운영",
      "fallbackPhone": "123",
      "phoneStatus": "official_page",
      "source": "한국전력공사_한전ON 사업소정보_20240913",
      "lastCheckedAt": "2026-06-23"
    },
    "세종지사": {
      "officeName": "세종지사",
      "officePhone": "044-861-4232",
      "officeAddress": "세종특별자치시 법원로 18",
      "departmentName": "전력공급부",
      "taskName": "전력공급방안 검토",
      "fallbackPhone": "123",
      "phoneStatus": "official_page",
      "source": "한국전력공사_한전ON 사업소정보_20240913",
      "lastCheckedAt": "2026-06-23"
    },
    "아산지사": {
      "officeName": "아산지사",
      "officePhone": "041-539-3236",
      "officeAddress": "충남 아산시 충무로 72번길 13",
      "departmentName": "전력공급부",
      "taskName": "[내선계기] 고·저압 신증설 업무 및 계기일반 업무(염치 인주 선장) / 전력량계 부속장치 및 공기구 관리 / 저압 전문회사 및 안전관리업무 / 고압 정기시험 관련 업무",
      "fallbackPhone": "123",
      "phoneStatus": "official_page",
      "source": "한국전력공사_한전ON 사업소정보_20240913",
      "lastCheckedAt": "2026-06-23"
    },
    "예산지사": {
      "officeName": "예산지사",
      "officePhone": "041-330-3235",
      "officeAddress": "충남 예산군 예산읍 금오대로 151",
      "departmentName": "전력공급부",
      "taskName": "신규·지장주·계획공사 설계·공사관리(예산대술신양광시) 분산형전원 지중화",
      "fallbackPhone": "123",
      "phoneStatus": "official_page",
      "source": "한국전력공사_한전ON 사업소정보_20240913",
      "lastCheckedAt": "2026-06-23"
    },
    "천안전력지사": {
      "officeName": "천안전력지사",
      "officePhone": "041-410-5352",
      "officeAddress": "충남 천안시 동남구 정골1길 7(구성동 267-1번지)",
      "departmentName": "송전부",
      "taskName": "송전설비 고장복구",
      "fallbackPhone": "123",
      "phoneStatus": "official_page",
      "source": "한국전력공사_한전ON 사업소정보_20240913",
      "lastCheckedAt": "2026-06-23"
    },
    "천안지사": {
      "officeName": "천안지사",
      "officePhone": "041-560-2232",
      "officeAddress": "충남 천안시 서북구 동서대로 77",
      "departmentName": "전력공급부",
      "taskName": "전력공급방안 검토",
      "fallbackPhone": "123",
      "phoneStatus": "official_page",
      "source": "한국전력공사_한전ON 사업소정보_20240913",
      "lastCheckedAt": "2026-06-23"
    },
    "청양전력지사": {
      "officeName": "청양전력지사",
      "officePhone": "041-940-1352",
      "officeAddress": "충남 청양군 청양읍 청수길 96",
      "departmentName": "송전팀",
      "taskName": "송전설비 고장복구",
      "fallbackPhone": "123",
      "phoneStatus": "official_page",
      "source": "한국전력공사_한전ON 사업소정보_20240913",
      "lastCheckedAt": "2026-06-23"
    },
    "청양지사": {
      "officeName": "청양지사",
      "officePhone": "041-940-1233",
      "officeAddress": "충남 청양군 청양읍 중앙로 37-6",
      "departmentName": "전력공급팀",
      "taskName": "신증설 설계 시공/지역담당자 상이",
      "fallbackPhone": "123",
      "phoneStatus": "official_page",
      "source": "한국전력공사_한전ON 사업소정보_20240913",
      "lastCheckedAt": "2026-06-23"
    },
    "태안지사": {
      "officeName": "태안지사",
      "officePhone": "041-671-1232",
      "officeAddress": "충남 태안군 태안읍 후곡로 53",
      "departmentName": "전력공급부",
      "taskName": "신증설 배전선로 이설공사 설계 시공(이원면 원북면 소원면 신축지장)",
      "fallbackPhone": "123",
      "phoneStatus": "official_page",
      "source": "한국전력공사_한전ON 사업소정보_20240913",
      "lastCheckedAt": "2026-06-23"
    },
    "홍성지사": {
      "officeName": "홍성지사",
      "officePhone": "041-630-2232",
      "officeAddress": "충남 홍성군 홍성읍 충서로 1417-6",
      "departmentName": "전력공급부",
      "taskName": "안전관리 품질 환경 업무",
      "fallbackPhone": "123",
      "phoneStatus": "official_page",
      "source": "한국전력공사_한전ON 사업소정보_20240913",
      "lastCheckedAt": "2026-06-23"
    },
    "기장지사": {
      "officeName": "기장지사",
      "officePhone": "051-720-3231",
      "officeAddress": "부산광역시 기장군 기장읍 청강로 24",
      "departmentName": "전력공급팀",
      "taskName": "신증설 설계 시공",
      "fallbackPhone": "123",
      "phoneStatus": "official_page",
      "source": "한국전력공사_한전ON 사업소정보_20240913",
      "lastCheckedAt": "2026-06-23"
    },
    "김해지사": {
      "officeName": "김해지사",
      "officePhone": "055-330-2233",
      "officeAddress": "경남 김해시 김해대로 2399",
      "departmentName": "전력공급부",
      "taskName": "신규공급 설계 및 시공(내외동 한림면)",
      "fallbackPhone": "123",
      "phoneStatus": "official_page",
      "source": "한국전력공사_한전ON 사업소정보_20240913",
      "lastCheckedAt": "2026-06-23"
    },
    "남부산지사": {
      "officeName": "남부산지사",
      "officePhone": "051-740-1232",
      "officeAddress": "부산광역시 해운대구 해운대해변로 113",
      "departmentName": "전력공급부",
      "taskName": "안전관리 품질 환경 업무",
      "fallbackPhone": "123",
      "phoneStatus": "official_page",
      "source": "한국전력공사_한전ON 사업소정보_20240913",
      "lastCheckedAt": "2026-06-23"
    },
    "동래지사": {
      "officeName": "동래지사",
      "officePhone": "051-520-2243",
      "officeAddress": "부산광역시 동래구 충렬대로 423",
      "departmentName": "전력공급부",
      "taskName": "고압송전(금정구) 저압송전(금정구)",
      "fallbackPhone": "123",
      "phoneStatus": "official_page",
      "source": "한국전력공사_한전ON 사업소정보_20240913",
      "lastCheckedAt": "2026-06-23"
    },
    "동부산전력지사": {
      "officeName": "동부산전력지사",
      "officePhone": "051-559-4352",
      "officeAddress": "부산광역시 기장군 철마면 반송로 1136",
      "departmentName": "송전부",
      "taskName": "품질 및 안전관리",
      "fallbackPhone": "123",
      "phoneStatus": "official_page",
      "source": "한국전력공사_한전ON 사업소정보_20240913",
      "lastCheckedAt": "2026-06-23"
    },
    "동울산지사": {
      "officeName": "동울산지사",
      "officePhone": "052-219-8233",
      "officeAddress": "울산광역시 북구 명촌23길 8",
      "departmentName": "전력공급부",
      "taskName": "안전관리 품질 환경 업무",
      "fallbackPhone": "123",
      "phoneStatus": "official_page",
      "source": "한국전력공사_한전ON 사업소정보_20240913",
      "lastCheckedAt": "2026-06-23"
    },
    "부산울산본부": {
      "officeName": "부산울산본부",
      "officePhone": "051-604-2233",
      "officeAddress": "부산광역시 부산진구 중앙대로 666번길 43",
      "departmentName": "전력공급부",
      "taskName": "신증설 설계 시공",
      "fallbackPhone": "123",
      "phoneStatus": "official_page",
      "source": "한국전력공사_한전ON 사업소정보_20240913",
      "lastCheckedAt": "2026-06-23"
    },
    "부산울산본부직할": {
      "officeName": "부산울산본부직할",
      "officePhone": "051-604-5233",
      "officeAddress": "부산광역시 부산진구 중앙대로 666번길 43",
      "departmentName": "전력공급부",
      "taskName": "신증설 설계 시공",
      "fallbackPhone": "123",
      "phoneStatus": "official_page",
      "source": "한국전력공사_한전ON 사업소정보_20240913",
      "lastCheckedAt": "2026-06-23"
    },
    "북부산전력지사": {
      "officeName": "북부산전력지사",
      "officePhone": "051-330-2351",
      "officeAddress": "부산광역시 북구 와석장터로 77",
      "departmentName": "송전부",
      "taskName": "송전설비 고장복구",
      "fallbackPhone": "123",
      "phoneStatus": "official_page",
      "source": "한국전력공사_한전ON 사업소정보_20240913",
      "lastCheckedAt": "2026-06-23"
    },
    "북부산지사": {
      "officeName": "북부산지사",
      "officePhone": "051-309-2234",
      "officeAddress": "부산광역시 사상구 백양대로 700번길 24",
      "departmentName": "전력공급부",
      "taskName": "전력공급방안 검토 분산형전원 선로용량 확인",
      "fallbackPhone": "123",
      "phoneStatus": "official_page",
      "source": "한국전력공사_한전ON 사업소정보_20240913",
      "lastCheckedAt": "2026-06-23"
    },
    "서부산전력지사": {
      "officeName": "서부산전력지사",
      "officePhone": "051-794-8351",
      "officeAddress": "부산시 사하구 감천항로 7",
      "departmentName": "송전팀",
      "taskName": "송전설비 순시점검",
      "fallbackPhone": "123",
      "phoneStatus": "official_page",
      "source": "한국전력공사_한전ON 사업소정보_20240913",
      "lastCheckedAt": "2026-06-23"
    },
    "서부산지사": {
      "officeName": "서부산지사",
      "officePhone": "051-250-9232",
      "officeAddress": "부산광역시 강서구 유통단지1로 41 부산T-PLEX 본관2층",
      "departmentName": "전력공급부",
      "taskName": "신증설 설계 시공",
      "fallbackPhone": "123",
      "phoneStatus": "official_page",
      "source": "한국전력공사_한전ON 사업소정보_20240913",
      "lastCheckedAt": "2026-06-23"
    },
    "서울산지사": {
      "officeName": "서울산지사",
      "officePhone": "052-255-4231",
      "officeAddress": "울산광역시 울주군 삼남읍 향교로 112",
      "departmentName": "전력공급팀",
      "taskName": "신증설 설계 및 시공 전력공급방안 검토(두동)",
      "fallbackPhone": "123",
      "phoneStatus": "official_page",
      "source": "한국전력공사_한전ON 사업소정보_20240913",
      "lastCheckedAt": "2026-06-23"
    },
    "양산지사": {
      "officeName": "양산지사",
      "officePhone": "055-380-3232",
      "officeAddress": "경남 양산시 고향의봄로 42",
      "departmentName": "전력공급부",
      "taskName": "안전관리 품질 환경 업무",
      "fallbackPhone": "123",
      "phoneStatus": "official_page",
      "source": "한국전력공사_한전ON 사업소정보_20240913",
      "lastCheckedAt": "2026-06-23"
    },
    "영도지사": {
      "officeName": "영도지사",
      "officePhone": "051-410-2222",
      "officeAddress": "부산광역시 영도구 남항남로9번길 61",
      "departmentName": "고객지원팀",
      "taskName": "고압 신증설 접수 지장전주 이설 접수",
      "fallbackPhone": "123",
      "phoneStatus": "official_page",
      "source": "한국전력공사_한전ON 사업소정보_20240913",
      "lastCheckedAt": "2026-06-23"
    },
    "울산전력지사": {
      "officeName": "울산전력지사",
      "officePhone": "052-270-4341",
      "officeAddress": "울산광역시 울주군 청량면 아랫개산길 29",
      "departmentName": "송전부",
      "taskName": "송전설비 보수계획 및 시공",
      "fallbackPhone": "123",
      "phoneStatus": "official_page",
      "source": "한국전력공사_한전ON 사업소정보_20240913",
      "lastCheckedAt": "2026-06-23"
    },
    "울산지사": {
      "officeName": "울산지사",
      "officePhone": "052-270-3232",
      "officeAddress": "울산광역시 남구 돋질로 181",
      "departmentName": "전력공급부",
      "taskName": "신증설 설계 시공",
      "fallbackPhone": "123",
      "phoneStatus": "official_page",
      "source": "한국전력공사_한전ON 사업소정보_20240913",
      "lastCheckedAt": "2026-06-23"
    },
    "중부산지사": {
      "officeName": "중부산지사",
      "officePhone": "051-240-3163",
      "officeAddress": "부산광역시 서구 까치고개로 252",
      "departmentName": "전력공급부",
      "taskName": "계기이상/시험/교환",
      "fallbackPhone": "123",
      "phoneStatus": "official_page",
      "source": "한국전력공사_한전ON 사업소정보_20240913",
      "lastCheckedAt": "2026-06-23"
    },
    "강북성북지사": {
      "officeName": "강북성북지사",
      "officePhone": "02-901-4232",
      "officeAddress": "서울특별시 강북구 도봉로 242",
      "departmentName": "전력공급부",
      "taskName": "유도장해 고조파 관련 업무",
      "fallbackPhone": "123",
      "phoneStatus": "official_page",
      "source": "한국전력공사_한전ON 사업소정보_20240913",
      "lastCheckedAt": "2026-06-23"
    },
    "광진성동지사": {
      "officeName": "광진성동지사",
      "officePhone": "02-2290-5232",
      "officeAddress": "서울특별시 성동구 마장로27길 13",
      "departmentName": "전력공급부",
      "taskName": "신증설 공사 설계 및 시공",
      "fallbackPhone": "123",
      "phoneStatus": "official_page",
      "source": "한국전력공사_한전ON 사업소정보_20240913",
      "lastCheckedAt": "2026-06-23"
    },
    "노원도봉지사": {
      "officeName": "노원도봉지사",
      "officePhone": "02-950-6232",
      "officeAddress": "서울특별시 노원구 노해로 429",
      "departmentName": "전력공급부",
      "taskName": "계기이상/시험/교환 업무 (노원구)",
      "fallbackPhone": "123",
      "phoneStatus": "official_page",
      "source": "한국전력공사_한전ON 사업소정보_20240913",
      "lastCheckedAt": "2026-06-23"
    },
    "동대문중랑지사": {
      "officeName": "동대문중랑지사",
      "officePhone": "02-970-4233",
      "officeAddress": "서울특별시 중랑구 동일로 862",
      "departmentName": "전력공급부",
      "taskName": "신증설 설계 시공",
      "fallbackPhone": "123",
      "phoneStatus": "official_page",
      "source": "한국전력공사_한전ON 사업소정보_20240913",
      "lastCheckedAt": "2026-06-23"
    },
    "마포용산지사": {
      "officeName": "마포용산지사",
      "officePhone": "02-710-2243",
      "officeAddress": "서울 마포구 토정로37길 38",
      "departmentName": "전력공급부",
      "taskName": "고압 계기이상 시험 교환 업무(용산구)",
      "fallbackPhone": "123",
      "phoneStatus": "official_page",
      "source": "한국전력공사_한전ON 사업소정보_20240913",
      "lastCheckedAt": "2026-06-23"
    },
    "서대문은평지사": {
      "officeName": "서대문은평지사",
      "officePhone": "02-350-2189",
      "officeAddress": "서울특별시 은평구 통일로 659",
      "departmentName": "전력공급부",
      "taskName": "사용전 점검",
      "fallbackPhone": "123",
      "phoneStatus": "official_page",
      "source": "한국전력공사_한전ON 사업소정보_20240913",
      "lastCheckedAt": "2026-06-23"
    },
    "서울본부": {
      "officeName": "서울본부",
      "officePhone": "02-758-3332",
      "officeAddress": "서울특별시 중구 남대문로 92",
      "departmentName": "전력공급부",
      "taskName": "계약업무",
      "fallbackPhone": "123",
      "phoneStatus": "official_page",
      "source": "한국전력공사_한전ON 사업소정보_20240913",
      "lastCheckedAt": "2026-06-23"
    },
    "서울본부직할": {
      "officeName": "서울본부직할",
      "officePhone": "02-758-3293",
      "officeAddress": "서울특별시 중구 남대문로 92",
      "departmentName": "전력공급부",
      "taskName": "사용전 점검 신규 고압송전 인입선 및 신증설 계기 신설(종로구)",
      "fallbackPhone": "123",
      "phoneStatus": "official_page",
      "source": "한국전력공사_한전ON 사업소정보_20240913",
      "lastCheckedAt": "2026-06-23"
    },
    "성동전력지사": {
      "officeName": "성동전력지사",
      "officePhone": null,
      "officeAddress": "서울특별시 성동구 마장로37길 17",
      "departmentName": null,
      "taskName": null,
      "fallbackPhone": "123",
      "phoneStatus": "unknown",
      "source": "한국전력공사_한전ON 사업소정보_20240913",
      "lastCheckedAt": "2026-06-23"
    },
    "중부전력지사": {
      "officeName": "중부전력지사",
      "officePhone": "02-320-7352",
      "officeAddress": "서울특별시 마포구 토정로 56",
      "departmentName": "송전팀",
      "taskName": "송전설비 고장복구",
      "fallbackPhone": "123",
      "phoneStatus": "official_page",
      "source": "한국전력공사_한전ON 사업소정보_20240913",
      "lastCheckedAt": "2026-06-23"
    },
    "강화지사": {
      "officeName": "강화지사",
      "officePhone": "032-930-2232",
      "officeAddress": "인천광역시 강화군 강화읍 강화대로 278(강화읍 갑곳리 350번지)",
      "departmentName": "전력공급부",
      "taskName": "신증설 설계 시공",
      "fallbackPhone": "123",
      "phoneStatus": "official_page",
      "source": "한국전력공사_한전ON 사업소정보_20240913",
      "lastCheckedAt": "2026-06-23"
    },
    "김포전력지사": {
      "officeName": "김포전력지사",
      "officePhone": null,
      "officeAddress": "인천광역시 서구 원당대로117번길 1(오류동김포전력지사)",
      "departmentName": null,
      "taskName": null,
      "fallbackPhone": "123",
      "phoneStatus": "unknown",
      "source": "한국전력공사_한전ON 사업소정보_20240913",
      "lastCheckedAt": "2026-06-23"
    },
    "김포지사": {
      "officeName": "김포지사",
      "officePhone": "031-980-7232",
      "officeAddress": "경기도 김포시 태장로 773",
      "departmentName": "전력공급부",
      "taskName": "신증설 설계 시공",
      "fallbackPhone": "123",
      "phoneStatus": "official_page",
      "source": "한국전력공사_한전ON 사업소정보_20240913",
      "lastCheckedAt": "2026-06-23"
    },
    "남인천지사": {
      "officeName": "남인천지사",
      "officePhone": "032-830-5262",
      "officeAddress": "인천광역시 연수구 비류대로 304",
      "departmentName": "전력공급부",
      "taskName": "[고압] 신규송전/수전설비 관련",
      "fallbackPhone": "123",
      "phoneStatus": "official_page",
      "source": "한국전력공사_한전ON 사업소정보_20240913",
      "lastCheckedAt": "2026-06-23"
    },
    "백령지사": {
      "officeName": "백령지사",
      "officePhone": "032-520-7143",
      "officeAddress": "인천광역시 옹진군 백령면 백령로 346",
      "departmentName": "고객지원팀",
      "taskName": "신증설 설계 시공",
      "fallbackPhone": "123",
      "phoneStatus": "official_page",
      "source": "한국전력공사_한전ON 사업소정보_20240913",
      "lastCheckedAt": "2026-06-23"
    },
    "부천지사": {
      "officeName": "부천지사",
      "officePhone": "032-650-1232",
      "officeAddress": "경기도 부천시 부천로 264번길 4",
      "departmentName": "전력공급부",
      "taskName": "신증설 설계 시공",
      "fallbackPhone": "123",
      "phoneStatus": "official_page",
      "source": "한국전력공사_한전ON 사업소정보_20240913",
      "lastCheckedAt": "2026-06-23"
    },
    "부평전력지사": {
      "officeName": "부평전력지사",
      "officePhone": "032-570-7353",
      "officeAddress": "인천광역시 부평구 동수로 113",
      "departmentName": "송전부",
      "taskName": "송전설비 고장복구(가공)",
      "fallbackPhone": "123",
      "phoneStatus": "official_page",
      "source": "한국전력공사_한전ON 사업소정보_20240913",
      "lastCheckedAt": "2026-06-23"
    },
    "서인천지사": {
      "officeName": "서인천지사",
      "officePhone": "032-560-1232",
      "officeAddress": "인천광역시 서구 청라커낼로 286 (청라동 157-4)",
      "departmentName": "전력공급부",
      "taskName": "안전관리 책임분계점 조작",
      "fallbackPhone": "123",
      "phoneStatus": "official_page",
      "source": "한국전력공사_한전ON 사업소정보_20240913",
      "lastCheckedAt": "2026-06-23"
    },
    "시흥전력지사": {
      "officeName": "시흥전력지사",
      "officePhone": "031-363-5322",
      "officeAddress": "인천광역시 연수구 갯벌로 12 미추홀타워 18층",
      "departmentName": "송전팀",
      "taskName": "송전설비 보수계획 및 시공",
      "fallbackPhone": "123",
      "phoneStatus": "official_page",
      "source": "한국전력공사_한전ON 사업소정보_20240913",
      "lastCheckedAt": "2026-06-23"
    },
    "시흥지사": {
      "officeName": "시흥지사",
      "officePhone": "031-310-3222",
      "officeAddress": "경기도 시흥시 은계중앙로 255",
      "departmentName": "전력공급부",
      "taskName": "사회복지시설 냉·난방기 설치 지원사업",
      "fallbackPhone": "123",
      "phoneStatus": "official_page",
      "source": "한국전력공사_한전ON 사업소정보_20240913",
      "lastCheckedAt": "2026-06-23"
    },
    "영종지사": {
      "officeName": "영종지사",
      "officePhone": "032-880-7217",
      "officeAddress": "인천광역시 중구 영종대로196번길 15-21",
      "departmentName": "고객지원팀",
      "taskName": "전기사용신청(신규증설) 상계거래",
      "fallbackPhone": "123",
      "phoneStatus": "official_page",
      "source": "한국전력공사_한전ON 사업소정보_20240913",
      "lastCheckedAt": "2026-06-23"
    },
    "인천본부": {
      "officeName": "인천본부",
      "officePhone": "032-520-7228",
      "officeAddress": "인천광역시 부평구 주부토로246",
      "departmentName": "전력공급부",
      "taskName": "안전관리 품질 환경 업무",
      "fallbackPhone": "123",
      "phoneStatus": "official_page",
      "source": "한국전력공사_한전ON 사업소정보_20240913",
      "lastCheckedAt": "2026-06-23"
    },
    "인천본부직할": {
      "officeName": "인천본부직할",
      "officePhone": "032-520-7231",
      "officeAddress": "인천광역시 부평구 주부토로246",
      "departmentName": "전력공급부",
      "taskName": "전력공급방안 검토",
      "fallbackPhone": "123",
      "phoneStatus": "official_page",
      "source": "한국전력공사_한전ON 사업소정보_20240913",
      "lastCheckedAt": "2026-06-23"
    },
    "제물포지사": {
      "officeName": "제물포지사",
      "officePhone": "032-880-1232",
      "officeAddress": "인천광역시 미추홀구 숙골로87번길 27 (도화동 999)",
      "departmentName": "전력공급부",
      "taskName": "전력공급방안 검토설계시공",
      "fallbackPhone": "123",
      "phoneStatus": "official_page",
      "source": "한국전력공사_한전ON 사업소정보_20240913",
      "lastCheckedAt": "2026-06-23"
    },
    "고창지사": {
      "officeName": "고창지사",
      "officePhone": "063-560-3277",
      "officeAddress": "전북 고창군 고창읍 중거리당산로 46",
      "departmentName": "전력공급부",
      "taskName": "분산형전원 기술업무",
      "fallbackPhone": "123",
      "phoneStatus": "official_page",
      "source": "한국전력공사_한전ON 사업소정보_20240913",
      "lastCheckedAt": "2026-06-23"
    },
    "군산전력지사": {
      "officeName": "군산전력지사",
      "officePhone": "063-450-3340",
      "officeAddress": "전북 군산시 호원대1길 216",
      "departmentName": "변전운영팀",
      "taskName": "변전설비 유지보수",
      "fallbackPhone": "123",
      "phoneStatus": "official_page",
      "source": "한국전력공사_한전ON 사업소정보_20240913",
      "lastCheckedAt": "2026-06-23"
    },
    "군산지사": {
      "officeName": "군산지사",
      "officePhone": "063-440-2236",
      "officeAddress": "전북 군산시 해망로 264",
      "departmentName": "전력공급부",
      "taskName": "태양광 신재생에너지 관리",
      "fallbackPhone": "123",
      "phoneStatus": "official_page",
      "source": "한국전력공사_한전ON 사업소정보_20240913",
      "lastCheckedAt": "2026-06-23"
    },
    "김제전력지사": {
      "officeName": "김제전력지사",
      "officePhone": "063-540-5452",
      "officeAddress": "전라북도 김제시 동서로 310(검산동 1117)",
      "departmentName": "송전팀",
      "taskName": "송전설비 고장복구",
      "fallbackPhone": "123",
      "phoneStatus": "official_page",
      "source": "한국전력공사_한전ON 사업소정보_20240913",
      "lastCheckedAt": "2026-06-23"
    },
    "김제지사": {
      "officeName": "김제지사",
      "officePhone": "063-540-2254",
      "officeAddress": "전북 김제시 금성로 83",
      "departmentName": "전력공급부",
      "taskName": "신재생에너지(태양광)관련 업무 - 용량검토",
      "fallbackPhone": "123",
      "phoneStatus": "official_page",
      "source": "한국전력공사_한전ON 사업소정보_20240913",
      "lastCheckedAt": "2026-06-23"
    },
    "남원지사": {
      "officeName": "남원지사",
      "officePhone": "063-620-2268",
      "officeAddress": "전북 남원시 충정로 119",
      "departmentName": "전력공급부",
      "taskName": "배전선로 순시",
      "fallbackPhone": "123",
      "phoneStatus": "official_page",
      "source": "한국전력공사_한전ON 사업소정보_20240913",
      "lastCheckedAt": "2026-06-23"
    },
    "남전주지사": {
      "officeName": "남전주지사",
      "officePhone": "063-249-5261",
      "officeAddress": "전북 전주시 완산구 모악로 4678",
      "departmentName": "전력공급부",
      "taskName": "내선 계량기",
      "fallbackPhone": "123",
      "phoneStatus": "official_page",
      "source": "한국전력공사_한전ON 사업소정보_20240913",
      "lastCheckedAt": "2026-06-23"
    },
    "무주지사": {
      "officeName": "무주지사",
      "officePhone": "063-320-6273",
      "officeAddress": "전북 무주군 무주읍 죽향로 31-16",
      "departmentName": "전력공급팀",
      "taskName": "신증설 설계 시공",
      "fallbackPhone": "123",
      "phoneStatus": "official_page",
      "source": "한국전력공사_한전ON 사업소정보_20240913",
      "lastCheckedAt": "2026-06-23"
    },
    "부안지사": {
      "officeName": "부안지사",
      "officePhone": "063-580-2288",
      "officeAddress": "전북 부안군 부안읍 신선길 1",
      "departmentName": "전력공급팀",
      "taskName": "신증설 설계 시공(주산면 보안면 행안면)",
      "fallbackPhone": "123",
      "phoneStatus": "official_page",
      "source": "한국전력공사_한전ON 사업소정보_20240913",
      "lastCheckedAt": "2026-06-23"
    },
    "순창지사": {
      "officeName": "순창지사",
      "officePhone": "063-650-3273",
      "officeAddress": "전북 순창군 순창읍 유등로 18",
      "departmentName": "전력공급팀",
      "taskName": "신증설 설계 시공",
      "fallbackPhone": "123",
      "phoneStatus": "official_page",
      "source": "한국전력공사_한전ON 사업소정보_20240913",
      "lastCheckedAt": "2026-06-23"
    },
    "익산지사": {
      "officeName": "익산지사",
      "officePhone": "063-839-4273",
      "officeAddress": "전북 익산시 석암로 15길 156",
      "departmentName": "전력공급부",
      "taskName": "고압 신증설(태양광 포함) 설계/시공",
      "fallbackPhone": "123",
      "phoneStatus": "official_page",
      "source": "한국전력공사_한전ON 사업소정보_20240913",
      "lastCheckedAt": "2026-06-23"
    },
    "임실지사": {
      "officeName": "임실지사",
      "officePhone": "063-640-5213",
      "officeAddress": "전북 임실군 임실읍 봉황로 245",
      "departmentName": "고객지원팀",
      "taskName": "신증설(저압/고압) 접수",
      "fallbackPhone": "123",
      "phoneStatus": "official_page",
      "source": "한국전력공사_한전ON 사업소정보_20240913",
      "lastCheckedAt": "2026-06-23"
    },
    "장수지사": {
      "officeName": "장수지사",
      "officePhone": "063-350-3236",
      "officeAddress": "전북 장수군 장수읍 장천로 138",
      "departmentName": "전력공급팀",
      "taskName": "신증설 배전선로이설공사 설계 시공 (천천면계북면)",
      "fallbackPhone": "123",
      "phoneStatus": "official_page",
      "source": "한국전력공사_한전ON 사업소정보_20240913",
      "lastCheckedAt": "2026-06-23"
    },
    "전북본부직할": {
      "officeName": "전북본부직할",
      "officePhone": "063-240-5243",
      "officeAddress": "전북 전주시 덕진구 백제대로 741",
      "departmentName": "전력공급부",
      "taskName": "사용전 점검 업무",
      "fallbackPhone": "123",
      "phoneStatus": "official_page",
      "source": "한국전력공사_한전ON 사업소정보_20240913",
      "lastCheckedAt": "2026-06-23"
    },
    "정읍지사": {
      "officeName": "정읍지사",
      "officePhone": "063-530-2268",
      "officeAddress": "전북 정읍시 서부로 5",
      "departmentName": "전력공급부",
      "taskName": "운영실(전기고장접수/복구 및 선로순시)",
      "fallbackPhone": "123",
      "phoneStatus": "official_page",
      "source": "한국전력공사_한전ON 사업소정보_20240913",
      "lastCheckedAt": "2026-06-23"
    },
    "진안지사": {
      "officeName": "진안지사",
      "officePhone": "063-430-3235",
      "officeAddress": "전북 진안군 진안읍 대괭이길 7-21",
      "departmentName": "전력공급팀",
      "taskName": "신증설 설계 시공(동항면 상전면 안천면)",
      "fallbackPhone": "123",
      "phoneStatus": "official_page",
      "source": "한국전력공사_한전ON 사업소정보_20240913",
      "lastCheckedAt": "2026-06-23"
    },
    "서귀포지사": {
      "officeName": "서귀포지사",
      "officePhone": "064-730-2278",
      "officeAddress": "제주특별자치도 서귀포시 신중로 56",
      "departmentName": "전력공급부",
      "taskName": "신재생연계 용량검토",
      "fallbackPhone": "123",
      "phoneStatus": "official_page",
      "source": "한국전력공사_한전ON 사업소정보_20240913",
      "lastCheckedAt": "2026-06-23"
    },
    "제주본부직할": {
      "officeName": "제주본부직할",
      "officePhone": "064-740-3432",
      "officeAddress": "제주특별자치도 제주시 문연로 36",
      "departmentName": "전력공급부",
      "taskName": "3MW미만 가공 및 분산형전원 신규업무",
      "fallbackPhone": "123",
      "phoneStatus": "official_page",
      "source": "한국전력공사_한전ON 사업소정보_20240913",
      "lastCheckedAt": "2026-06-23"
    },
    "제주전력지사": {
      "officeName": "제주전력지사",
      "officePhone": "064-729-3351",
      "officeAddress": "제주특별자치도 제주시 가령로 68",
      "departmentName": "송전부",
      "taskName": "품질 및 안전관리",
      "fallbackPhone": "123",
      "phoneStatus": "official_page",
      "source": "한국전력공사_한전ON 사업소정보_20240913",
      "lastCheckedAt": "2026-06-23"
    },
    "단양지사": {
      "officeName": "단양지사",
      "officePhone": "043-420-2272",
      "officeAddress": "충북 단양군 단양읍 중앙1로 27-6",
      "departmentName": "전력공급팀",
      "taskName": "신증설 설계 시공(대강 단성)",
      "fallbackPhone": "123",
      "phoneStatus": "official_page",
      "source": "한국전력공사_한전ON 사업소정보_20240913",
      "lastCheckedAt": "2026-06-23"
    },
    "동청주지사": {
      "officeName": "동청주지사",
      "officePhone": "043-230-8238",
      "officeAddress": "충북 청주시 청원구 향군로 25",
      "departmentName": "전력공급부",
      "taskName": "계기이상/시험/교환 등 전력량계 관련 업무(미원낭성산성명암용담용정금천용암가덕월오운동방서평촌지북)",
      "fallbackPhone": "123",
      "phoneStatus": "official_page",
      "source": "한국전력공사_한전ON 사업소정보_20240913",
      "lastCheckedAt": "2026-06-23"
    },
    "보은지사": {
      "officeName": "보은지사",
      "officePhone": "043-540-2286",
      "officeAddress": "충북 보은군 보은읍 장신로 40",
      "departmentName": "전력공급팀",
      "taskName": "신증설 설계 시공",
      "fallbackPhone": "123",
      "phoneStatus": "official_page",
      "source": "한국전력공사_한전ON 사업소정보_20240913",
      "lastCheckedAt": "2026-06-23"
    },
    "영동지사": {
      "officeName": "영동지사",
      "officePhone": "043-740-2272",
      "officeAddress": "충북 영동군 영동읍 학산영동로 1149",
      "departmentName": "전력공급팀",
      "taskName": "신증설 설계 시공",
      "fallbackPhone": "123",
      "phoneStatus": "official_page",
      "source": "한국전력공사_한전ON 사업소정보_20240913",
      "lastCheckedAt": "2026-06-23"
    },
    "옥천지사": {
      "officeName": "옥천지사",
      "officePhone": "043-730-0232",
      "officeAddress": "충북 옥천군 옥천읍 삼양로 70",
      "departmentName": "고객지원팀",
      "taskName": "전기사용신청 업무",
      "fallbackPhone": "123",
      "phoneStatus": "official_page",
      "source": "한국전력공사_한전ON 사업소정보_20240913",
      "lastCheckedAt": "2026-06-23"
    },
    "음성지사": {
      "officeName": "음성지사",
      "officePhone": "043-870-3252",
      "officeAddress": "충북 음성군 음성읍 시장로80번길 23",
      "departmentName": "고객지원팀",
      "taskName": "전기사용신청(감곡면 생극면 음성읍 소이면 원남면 삼성면) 신재생에너지(요금상계거래)",
      "fallbackPhone": "123",
      "phoneStatus": "official_page",
      "source": "한국전력공사_한전ON 사업소정보_20240913",
      "lastCheckedAt": "2026-06-23"
    },
    "제천지사": {
      "officeName": "제천지사",
      "officePhone": "043-640-2236",
      "officeAddress": "충북 제천시 풍양로 57",
      "departmentName": "전력공급부",
      "taskName": "신증설 및 분산형전원 설계 및 시공(청풍수산덕산한수금성동량면 지동리(충주)산척면 명서리(충주))",
      "fallbackPhone": "123",
      "phoneStatus": "official_page",
      "source": "한국전력공사_한전ON 사업소정보_20240913",
      "lastCheckedAt": "2026-06-23"
    },
    "증평괴산지사": {
      "officeName": "증평괴산지사",
      "officePhone": "043-835-2234",
      "officeAddress": "충북 증평군 증평읍 충청대로 1829",
      "departmentName": "전력공급부",
      "taskName": "계기이상/시험/교환 업무",
      "fallbackPhone": "123",
      "phoneStatus": "official_page",
      "source": "한국전력공사_한전ON 사업소정보_20240913",
      "lastCheckedAt": "2026-06-23"
    },
    "진천지사": {
      "officeName": "진천지사",
      "officePhone": "043-539-2268",
      "officeAddress": "충북 진천군 진천읍 상산로 18",
      "departmentName": "전력공급부 배전운영실",
      "taskName": "전기 고장 신고",
      "fallbackPhone": "123",
      "phoneStatus": "official_page",
      "source": "한국전력공사_한전ON 사업소정보_20240913",
      "lastCheckedAt": "2026-06-23"
    },
    "청주전력지사": {
      "officeName": "청주전력지사",
      "officePhone": "043-229-0330",
      "officeAddress": "충북 청주시 서원구 남이면 문동길 147",
      "departmentName": "송전부",
      "taskName": "품질 및 안전관리",
      "fallbackPhone": "123",
      "phoneStatus": "official_page",
      "source": "한국전력공사_한전ON 사업소정보_20240913",
      "lastCheckedAt": "2026-06-23"
    },
    "충북본부": {
      "officeName": "충북본부",
      "officePhone": "043-251-2473",
      "officeAddress": "충북 청주시 서원구 구룡산로 51",
      "departmentName": "배전총괄팀",
      "taskName": "신증설 설계 시공",
      "fallbackPhone": "123",
      "phoneStatus": "official_page",
      "source": "한국전력공사_한전ON 사업소정보_20240913",
      "lastCheckedAt": "2026-06-23"
    },
    "충북본부 직할": {
      "officeName": "충북본부 직할",
      "officePhone": "043-251-2392",
      "officeAddress": "충북 청주시 서원구 구룡산로 51",
      "departmentName": "전력공급부",
      "taskName": "분산형전원 기술검토",
      "fallbackPhone": "123",
      "phoneStatus": "official_page",
      "source": "한국전력공사_한전ON 사업소정보_20240913",
      "lastCheckedAt": "2026-06-23"
    },
    "충북본부직할": {
      "officeName": "충북본부직할",
      "officePhone": "043-251-2392",
      "officeAddress": "충북 청주시 서원구 구룡산로 51",
      "departmentName": "전력공급부",
      "taskName": "분산형전원 기술검토",
      "fallbackPhone": "123",
      "phoneStatus": "official_page",
      "source": "한국전력공사_한전ON 사업소정보_20240913",
      "lastCheckedAt": "2026-06-23"
    },
    "충주전력지사": {
      "officeName": "충주전력지사",
      "officePhone": "043-720-3352",
      "officeAddress": "충북 충주시 목행산단1로 27",
      "departmentName": "송전팀",
      "taskName": "송전설비 보수계획 및 시공",
      "fallbackPhone": "123",
      "phoneStatus": "official_page",
      "source": "한국전력공사_한전ON 사업소정보_20240913",
      "lastCheckedAt": "2026-06-23"
    },
    "충주지사": {
      "officeName": "충주지사",
      "officePhone": "043-840-4247",
      "officeAddress": "충북 충주시 탄금대로 130",
      "departmentName": "전력공급부",
      "taskName": "사용전 점검",
      "fallbackPhone": "123",
      "phoneStatus": "official_page",
      "source": "한국전력공사_한전ON 사업소정보_20240913",
      "lastCheckedAt": "2026-06-23"
    }
  }
}
